{"box_data": [{"position": {"minX": 348.75, "minY": 219.625, "maxX": 515.0, "maxY": 387.5}, "class_id": 0, "box_caption": "bus 0.002", "scores": {"class_score": 0.0015439987182617188}, "domain": "pixel"}, {"position": {"minX": 349.0, "minY": 59.9375, "maxX": 515.0, "maxY": 227.0}, "class_id": 0, "box_caption": "bus 0.002", "scores": {"class_score": 0.0015430450439453125}, "domain": "pixel"}, {"position": {"minX": 349.25, "minY": 155.625, "maxX": 515.0, "maxY": 323.0}, "class_id": 0, "box_caption": "bus 0.002", "scores": {"class_score": 0.0015401840209960938}, "domain": "pixel"}, {"position": {"minX": 349.25, "minY": -4.25, "maxX": 515.0, "maxY": 163.125}, "class_id": 0, "box_caption": "bus 0.002", "scores": {"class_score": 0.0015401840209960938}, "domain": "pixel"}, {"position": {"minX": 61.375, "minY": 124.375, "maxX": 226.625, "maxY": 290.0}, "class_id": 0, "box_caption": "bus 0.001", "scores": {"class_score": 0.0014963150024414062}, "domain": "pixel"}, {"position": {"minX": 363.0, "minY": 246.25, "maxX": 501.0, "maxY": 361.75}, "class_id": 0, "box_caption": "bus 0.001", "scores": {"class_score": 0.0014801025390625}, "domain": "pixel"}, {"position": {"minX": 361.5, "minY": -36.75, "maxX": 504.5, "maxY": 70.5625}, "class_id": 0, "box_caption": "bus 0.001", "scores": {"class_score": 0.0014781951904296875}, "domain": "pixel"}, {"position": {"minX": 15.7265625, "minY": 261.5, "maxX": 46.5, "maxY": 306.0}, "class_id": 2, "box_caption": "0 0.001", "scores": {"class_score": 0.001476287841796875}, "domain": "pixel"}, {"position": {"minX": 363.0, "minY": 150.75, "maxX": 501.5, "maxY": 265.25}, "class_id": 0, "box_caption": "bus 0.001", "scores": {"class_score": 0.001476287841796875}, "domain": "pixel"}, {"position": {"minX": 363.25, "minY": 214.5, "maxX": 501.25, "maxY": 329.5}, "class_id": 0, "box_caption": "bus 0.001", "scores": {"class_score": 0.0014753341674804688}, "domain": "pixel"}, {"position": {"minX": 363.25, "minY": 182.5, "maxX": 501.25, "maxY": 297.5}, "class_id": 0, "box_caption": "bus 0.001", "scores": {"class_score": 0.0014753341674804688}, "domain": "pixel"}, {"position": {"minX": 362.0, "minY": -7.375, "maxX": 503.5, "maxY": 104.1875}, "class_id": 0, "box_caption": "bus 0.001", "scores": {"class_score": 0.0014753341674804688}, "domain": "pixel"}, {"position": {"minX": 363.25, "minY": 22.5625, "maxX": 501.25, "maxY": 137.5}, "class_id": 0, "box_caption": "bus 0.001", "scores": {"class_score": 0.0014734268188476562}, "domain": "pixel"}, {"position": {"minX": 363.0, "minY": 86.625, "maxX": 501.5, "maxY": 201.375}, "class_id": 0, "box_caption": "bus 0.001", "scores": {"class_score": 0.0014734268188476562}, "domain": "pixel"}, {"position": {"minX": 363.0, "minY": 118.375, "maxX": 501.0, "maxY": 233.625}, "class_id": 0, "box_caption": "bus 0.001", "scores": {"class_score": 0.00147247314453125}, "domain": "pixel"}, {"position": {"minX": 169.125, "minY": -37.15625, "maxX": 313.0, "maxY": 70.875}, "class_id": 0, "box_caption": "bus 0.001", "scores": {"class_score": 0.0014715194702148438}, "domain": "pixel"}, {"position": {"minX": 363.0, "minY": 54.5625, "maxX": 501.5, "maxY": 169.5}, "class_id": 0, "box_caption": "bus 0.001", "scores": {"class_score": 0.0014696121215820312}, "domain": "pixel"}, {"position": {"minX": 233.375, "minY": -37.15625, "maxX": 376.5, "maxY": 70.875}, "class_id": 0, "box_caption": "bus 0.001", "scores": {"class_score": 0.001468658447265625}, "domain": "pixel"}, {"position": {"minX": 73.375, "minY": -37.15625, "maxX": 216.625, "maxY": 70.875}, "class_id": 0, "box_caption": "bus 0.001", "scores": {"class_score": 0.0014657974243164062}, "domain": "pixel"}, {"position": {"minX": 9.375, "minY": -37.15625, "maxX": 152.625, "maxY": 70.875}, "class_id": 0, "box_caption": "bus 0.001", "scores": {"class_score": 0.0014657974243164062}, "domain": "pixel"}, {"position": {"minX": 297.5, "minY": -37.15625, "maxX": 440.5, "maxY": 70.875}, "class_id": 0, "box_caption": "bus 0.001", "scores": {"class_score": 0.0014657974243164062}, "domain": "pixel"}, {"position": {"minX": 330.75, "minY": 114.9375, "maxX": 467.75, "maxY": 236.25}, "class_id": 0, "box_caption": "bus 0.001", "scores": {"class_score": 0.0014638900756835938}, "domain": "pixel"}, {"position": {"minX": -56.3125, "minY": -38.59375, "maxX": 89.6875, "maxY": 71.75}, "class_id": 0, "box_caption": "bus 0.001", "scores": {"class_score": 0.0014619827270507812}, "domain": "pixel"}, {"position": {"minX": 123.375, "minY": -2.5625, "maxX": 293.0, "maxY": 161.0}, "class_id": 0, "box_caption": "bus 0.001", "scores": {"class_score": 0.0014600753784179688}, "domain": "pixel"}, {"position": {"minX": 318.0, "minY": 189.0, "maxX": 482.0, "maxY": 353.5}, "class_id": 0, "box_caption": "bus 0.001", "scores": {"class_score": 0.0014562606811523438}, "domain": "pixel"}, {"position": {"minX": 360.5, "minY": 276.0, "maxX": 501.5, "maxY": 397.0}, "class_id": 0, "box_caption": "bus 0.001", "scores": {"class_score": 0.0014543533325195312}, "domain": "pixel"}, {"position": {"minX": 16.765625, "minY": 212.5, "maxX": 45.875, "maxY": 259.5}, "class_id": 2, "box_caption": "0 0.001", "scores": {"class_score": 0.0014495849609375}, "domain": "pixel"}, {"position": {"minX": 27.0625, "minY": 60.875, "maxX": 198.0, "maxY": 225.625}, "class_id": 0, "box_caption": "bus 0.001", "scores": {"class_score": 0.0014486312866210938}, "domain": "pixel"}, {"position": {"minX": -1.75, "minY": 125.0625, "maxX": 161.375, "maxY": 289.5}, "class_id": 0, "box_caption": "bus 0.001", "scores": {"class_score": 0.0014467239379882812}, "domain": "pixel"}, {"position": {"minX": 199.25, "minY": 52.125, "maxX": 344.75, "maxY": 172.0}, "class_id": 0, "box_caption": "bus 0.001", "scores": {"class_score": 0.001445770263671875}, "domain": "pixel"}, {"position": {"minX": 62.0, "minY": -2.625, "maxX": 225.5, "maxY": 161.25}, "class_id": 0, "box_caption": "bus 0.001", "scores": {"class_score": 0.0014448165893554688}, "domain": "pixel"}, {"position": {"minX": -56.4375, "minY": -11.65625, "maxX": 88.9375, "maxY": 107.625}, "class_id": 0, "box_caption": "bus 0.001", "scores": {"class_score": 0.0014448165893554688}, "domain": "pixel"}, {"position": {"minX": -56.625, "minY": 244.25, "maxX": 89.0, "maxY": 363.75}, "class_id": 0, "box_caption": "bus 0.001", "scores": {"class_score": 0.0014429092407226562}, "domain": "pixel"}, {"position": {"minX": 222.25, "minY": 190.25, "maxX": 385.25, "maxY": 352.75}, "class_id": 0, "box_caption": "bus 0.001", "scores": {"class_score": 0.00144195556640625}, "domain": "pixel"}, {"position": {"minX": 201.0, "minY": 148.875, "maxX": 341.5, "maxY": 267.5}, "class_id": 0, "box_caption": "bus 0.001", "scores": {"class_score": 0.0014410018920898438}, "domain": "pixel"}, {"position": {"minX": 16.90625, "minY": 244.25, "maxX": 45.84375, "maxY": 291.75}, "class_id": 2, "box_caption": "0 0.001", "scores": {"class_score": 0.0014400482177734375}, "domain": "pixel"}, {"position": {"minX": -56.1875, "minY": 148.125, "maxX": 88.5625, "maxY": 267.75}, "class_id": 0, "box_caption": "bus 0.001", "scores": {"class_score": 0.0014400482177734375}, "domain": "pixel"}, {"position": {"minX": -56.1875, "minY": 116.125, "maxX": 88.5625, "maxY": 235.875}, "class_id": 0, "box_caption": "bus 0.001", "scores": {"class_score": 0.0014400482177734375}, "domain": "pixel"}, {"position": {"minX": -1.9375, "minY": -2.5, "maxX": 161.5, "maxY": 161.125}, "class_id": 0, "box_caption": "bus 0.001", "scores": {"class_score": 0.0014400482177734375}, "domain": "pixel"}, {"position": {"minX": 106.5, "minY": 211.75, "maxX": 245.25, "maxY": 331.75}, "class_id": 0, "box_caption": "bus 0.001", "scores": {"class_score": 0.0014390945434570312}, "domain": "pixel"}, {"position": {"minX": 169.75, "minY": -11.03125, "maxX": 311.25, "maxY": 107.125}, "class_id": 0, "box_caption": "bus 0.001", "scores": {"class_score": 0.0014390945434570312}, "domain": "pixel"}, {"position": {"minX": 42.25, "minY": 116.875, "maxX": 182.5, "maxY": 235.125}, "class_id": 0, "box_caption": "bus 0.001", "scores": {"class_score": 0.0014371871948242188}, "domain": "pixel"}, {"position": {"minX": 42.8125, "minY": 149.375, "maxX": 181.75, "maxY": 266.75}, "class_id": 0, "box_caption": "bus 0.001", "scores": {"class_score": 0.0014371871948242188}, "domain": "pixel"}, {"position": {"minX": 42.5, "minY": 20.6875, "maxX": 182.0, "maxY": 139.25}, "class_id": 0, "box_caption": "bus 0.001", "scores": {"class_score": 0.0014371871948242188}, "domain": "pixel"}, {"position": {"minX": -56.15625, "minY": 20.15625, "maxX": 88.625, "maxY": 139.875}, "class_id": 0, "box_caption": "bus 0.001", "scores": {"class_score": 0.0014362335205078125}, "domain": "pixel"}, {"position": {"minX": -56.1875, "minY": 212.0, "maxX": 88.5625, "maxY": 332.0}, "class_id": 0, "box_caption": "bus 0.001", "scores": {"class_score": 0.0014362335205078125}, "domain": "pixel"}, {"position": {"minX": -56.1875, "minY": 84.125, "maxX": 88.5625, "maxY": 203.875}, "class_id": 0, "box_caption": "bus 0.001", "scores": {"class_score": 0.0014362335205078125}, "domain": "pixel"}, {"position": {"minX": -56.1875, "minY": 180.0, "maxX": 88.5625, "maxY": 300.0}, "class_id": 0, "box_caption": "bus 0.001", "scores": {"class_score": 0.0014362335205078125}, "domain": "pixel"}, {"position": {"minX": -56.1875, "minY": 52.15625, "maxX": 88.5625, "maxY": 171.875}, "class_id": 0, "box_caption": "bus 0.001", "scores": {"class_score": 0.0014362335205078125}, "domain": "pixel"}, {"position": {"minX": 298.5, "minY": 212.875, "maxX": 438.0, "maxY": 331.25}, "class_id": 0, "box_caption": "bus 0.001", "scores": {"class_score": 0.0014362335205078125}, "domain": "pixel"}, {"position": {"minX": 106.625, "minY": 20.40625, "maxX": 245.125, "maxY": 139.375}, "class_id": 0, "box_caption": "bus 0.001", "scores": {"class_score": 0.001434326171875}, "domain": "pixel"}, {"position": {"minX": 75.0, "minY": 180.625, "maxX": 213.0, "maxY": 299.0}, "class_id": 0, "box_caption": "bus 0.001", "scores": {"class_score": 0.001434326171875}, "domain": "pixel"}, {"position": {"minX": 10.5, "minY": 52.6875, "maxX": 150.0, "maxY": 171.25}, "class_id": 0, "box_caption": "bus 0.001", "scores": {"class_score": 0.001434326171875}, "domain": "pixel"}, {"position": {"minX": 202.375, "minY": 212.75, "maxX": 342.0, "maxY": 331.25}, "class_id": 0, "box_caption": "bus 0.001", "scores": {"class_score": 0.001434326171875}, "domain": "pixel"}, {"position": {"minX": 298.5, "minY": 180.75, "maxX": 438.0, "maxY": 299.25}, "class_id": 0, "box_caption": "bus 0.001", "scores": {"class_score": 0.001434326171875}, "domain": "pixel"}, {"position": {"minX": 200.25, "minY": 117.3125, "maxX": 342.75, "maxY": 235.25}, "class_id": 0, "box_caption": "bus 0.001", "scores": {"class_score": 0.001434326171875}, "domain": "pixel"}, {"position": {"minX": 10.375, "minY": 84.625, "maxX": 150.125, "maxY": 203.375}, "class_id": 0, "box_caption": "bus 0.001", "scores": {"class_score": 0.0014333724975585938}, "domain": "pixel"}, {"position": {"minX": 102.375, "minY": 53.75, "maxX": 246.875, "maxY": 171.25}, "class_id": 0, "box_caption": "bus 0.001", "scores": {"class_score": 0.0014333724975585938}, "domain": "pixel"}, {"position": {"minX": 202.125, "minY": 180.875, "maxX": 343.0, "maxY": 299.25}, "class_id": 0, "box_caption": "bus 0.001", "scores": {"class_score": 0.0014333724975585938}, "domain": "pixel"}, {"position": {"minX": 136.75, "minY": 179.75, "maxX": 279.25, "maxY": 300.25}, "class_id": 0, "box_caption": "bus 0.001", "scores": {"class_score": 0.0014314651489257812}, "domain": "pixel"}, {"position": {"minX": 17.046875, "minY": 274.5, "maxX": 45.875, "maxY": 325.5}, "class_id": 2, "box_caption": "0 0.001", "scores": {"class_score": 0.001430511474609375}, "domain": "pixel"}, {"position": {"minX": 170.5, "minY": 18.21875, "maxX": 307.5, "maxY": 141.75}, "class_id": 0, "box_caption": "bus 0.001", "scores": {"class_score": 0.001430511474609375}, "domain": "pixel"}, {"position": {"minX": 28.1875, "minY": 158.0, "maxX": 196.0, "maxY": 320.5}, "class_id": 0, "box_caption": "bus 0.001", "scores": {"class_score": 0.001430511474609375}, "domain": "pixel"}, {"position": {"minX": 314.5, "minY": 253.5, "maxX": 485.0, "maxY": 418.5}, "class_id": 0, "box_caption": "bus 0.001", "scores": {"class_score": 0.0014295578002929688}, "domain": "pixel"}, {"position": {"minX": 250.375, "minY": 93.9375, "maxX": 422.5, "maxY": 258.0}, "class_id": 0, "box_caption": "bus 0.001", "scores": {"class_score": 0.0014295578002929688}, "domain": "pixel"}, {"position": {"minX": 200.125, "minY": 83.3125, "maxX": 344.0, "maxY": 204.75}, "class_id": 0, "box_caption": "bus 0.001", "scores": {"class_score": 0.0014286041259765625}, "domain": "pixel"}, {"position": {"minX": 41.125, "minY": 211.875, "maxX": 183.375, "maxY": 332.25}, "class_id": 0, "box_caption": "bus 0.001", "scores": {"class_score": 0.0014286041259765625}, "domain": "pixel"}, {"position": {"minX": -37.46875, "minY": 253.75, "maxX": 132.875, "maxY": 418.25}, "class_id": 0, "box_caption": "bus 0.001", "scores": {"class_score": 0.0014276504516601562}, "domain": "pixel"}, {"position": {"minX": 155.0, "minY": 253.5, "maxX": 324.25, "maxY": 418.5}, "class_id": 0, "box_caption": "bus 0.001", "scores": {"class_score": 0.00142669677734375}, "domain": "pixel"}, {"position": {"minX": 90.75, "minY": 253.5, "maxX": 260.5, "maxY": 418.5}, "class_id": 0, "box_caption": "bus 0.001", "scores": {"class_score": 0.00142669677734375}, "domain": "pixel"}, {"position": {"minX": 297.5, "minY": 84.375, "maxX": 438.5, "maxY": 203.625}, "class_id": 0, "box_caption": "bus 0.001", "scores": {"class_score": 0.00142669677734375}, "domain": "pixel"}, {"position": {"minX": 136.75, "minY": 148.25, "maxX": 279.25, "maxY": 267.75}, "class_id": 0, "box_caption": "bus 0.001", "scores": {"class_score": 0.00142669677734375}, "domain": "pixel"}, {"position": {"minX": 219.0, "minY": 253.5, "maxX": 388.5, "maxY": 418.5}, "class_id": 0, "box_caption": "bus 0.001", "scores": {"class_score": 0.00142669677734375}, "domain": "pixel"}, {"position": {"minX": 265.75, "minY": -10.4375, "maxX": 407.75, "maxY": 106.875}, "class_id": 0, "box_caption": "bus 0.001", "scores": {"class_score": 0.0014257431030273438}, "domain": "pixel"}, {"position": {"minX": 41.625, "minY": -10.4375, "maxX": 183.625, "maxY": 106.875}, "class_id": 0, "box_caption": "bus 0.001", "scores": {"class_score": 0.0014257431030273438}, "domain": "pixel"}, {"position": {"minX": 234.125, "minY": 20.53125, "maxX": 374.5, "maxY": 139.5}, "class_id": 0, "box_caption": "bus 0.001", "scores": {"class_score": 0.0014257431030273438}, "domain": "pixel"}, {"position": {"minX": 105.625, "minY": -10.4375, "maxX": 247.625, "maxY": 106.875}, "class_id": 0, "box_caption": "bus 0.001", "scores": {"class_score": 0.0014257431030273438}, "domain": "pixel"}, {"position": {"minX": 16.609375, "minY": 52.90625, "maxX": 45.6875, "maxY": 99.0}, "class_id": 2, "box_caption": "0 0.001", "scores": {"class_score": 0.0014257431030273438}, "domain": "pixel"}, {"position": {"minX": 136.375, "minY": 116.0625, "maxX": 279.5, "maxY": 236.25}, "class_id": 0, "box_caption": "bus 0.001", "scores": {"class_score": 0.0014238357543945312}, "domain": "pixel"}, {"position": {"minX": 136.25, "minY": 84.0, "maxX": 279.5, "maxY": 204.25}, "class_id": 0, "box_caption": "bus 0.001", "scores": {"class_score": 0.0014238357543945312}, "domain": "pixel"}, {"position": {"minX": 222.5, "minY": 29.25, "maxX": 385.0, "maxY": 193.625}, "class_id": 0, "box_caption": "bus 0.001", "scores": {"class_score": 0.001422882080078125}, "domain": "pixel"}, {"position": {"minX": 298.0, "minY": 20.15625, "maxX": 438.5, "maxY": 139.875}, "class_id": 0, "box_caption": "bus 0.001", "scores": {"class_score": 0.001422882080078125}, "domain": "pixel"}, {"position": {"minX": 284.0, "minY": 126.1875, "maxX": 452.0, "maxY": 288.5}, "class_id": 0, "box_caption": "bus 0.001", "scores": {"class_score": 0.0014219284057617188}, "domain": "pixel"}, {"position": {"minX": 124.1875, "minY": 222.375, "maxX": 291.0, "maxY": 385.0}, "class_id": 0, "box_caption": "bus 0.001", "scores": {"class_score": 0.0014219284057617188}, "domain": "pixel"}, {"position": {"minX": 317.5, "minY": 30.25, "maxX": 482.0, "maxY": 192.5}, "class_id": 0, "box_caption": "bus 0.001", "scores": {"class_score": 0.0014209747314453125}, "domain": "pixel"}, {"position": {"minX": 26.75, "minY": 253.5, "maxX": 196.5, "maxY": 418.5}, "class_id": 0, "box_caption": "bus 0.001", "scores": {"class_score": 0.0014209747314453125}, "domain": "pixel"}, {"position": {"minX": 16.84375, "minY": 181.0, "maxX": 45.6875, "maxY": 227.0}, "class_id": 2, "box_caption": "0 0.001", "scores": {"class_score": 0.0014209747314453125}, "domain": "pixel"}, {"position": {"minX": 252.75, "minY": 222.25, "maxX": 418.75, "maxY": 384.75}, "class_id": 0, "box_caption": "bus 0.001", "scores": {"class_score": 0.0014200210571289062}, "domain": "pixel"}, {"position": {"minX": 188.75, "minY": 222.25, "maxX": 354.75, "maxY": 384.75}, "class_id": 0, "box_caption": "bus 0.001", "scores": {"class_score": 0.0014200210571289062}, "domain": "pixel"}, {"position": {"minX": -56.5, "minY": 277.5, "maxX": 88.0, "maxY": 396.0}, "class_id": 0, "box_caption": "bus 0.001", "scores": {"class_score": 0.0014181137084960938}, "domain": "pixel"}, {"position": {"minX": 88.875, "minY": 96.875, "maxX": 266.5, "maxY": 253.375}, "class_id": 0, "box_caption": "bus 0.001", "scores": {"class_score": 0.0014171600341796875}, "domain": "pixel"}, {"position": {"minX": 254.375, "minY": 158.5, "maxX": 417.0, "maxY": 320.5}, "class_id": 0, "box_caption": "bus 0.001", "scores": {"class_score": 0.0014171600341796875}, "domain": "pixel"}, {"position": {"minX": 72.5, "minY": 88.125, "maxX": 216.5, "maxY": 201.375}, "class_id": 0, "box_caption": "bus 0.001", "scores": {"class_score": 0.0014162063598632812}, "domain": "pixel"}, {"position": {"minX": 8.75, "minY": 245.75, "maxX": 152.25, "maxY": 363.25}, "class_id": 0, "box_caption": "bus 0.001", "scores": {"class_score": 0.001415252685546875}, "domain": "pixel"}, {"position": {"minX": 16.796875, "minY": 68.875, "maxX": 45.6875, "maxY": 115.125}, "class_id": 2, "box_caption": "0 0.001", "scores": {"class_score": 0.001415252685546875}, "domain": "pixel"}, {"position": {"minX": 297.0, "minY": 52.28125, "maxX": 439.5, "maxY": 172.0}, "class_id": 0, "box_caption": "bus 0.001", "scores": {"class_score": 0.0014133453369140625}, "domain": "pixel"}, {"position": {"minX": 89.1875, "minY": 160.0, "maxX": 265.5, "maxY": 318.5}, "class_id": 0, "box_caption": "bus 0.001", "scores": {"class_score": 0.0014123916625976562}, "domain": "pixel"}, {"position": {"minX": 298.0, "minY": 244.125, "maxX": 438.5, "maxY": 363.75}, "class_id": 0, "box_caption": "bus 0.001", "scores": {"class_score": 0.0014123916625976562}, "domain": "pixel"}, {"position": {"minX": 16.828125, "minY": 164.875, "maxX": 45.6875, "maxY": 211.125}, "class_id": 2, "box_caption": "0 0.001", "scores": {"class_score": 0.0014123916625976562}, "domain": "pixel"}, {"position": {"minX": 16.828125, "minY": 132.875, "maxX": 45.6875, "maxY": 179.125}, "class_id": 2, "box_caption": "0 0.001", "scores": {"class_score": 0.0014123916625976562}, "domain": "pixel"}, {"position": {"minX": 16.84375, "minY": 100.875, "maxX": 45.6875, "maxY": 147.125}, "class_id": 2, "box_caption": "0 0.001", "scores": {"class_score": 0.0014123916625976562}, "domain": "pixel"}, {"position": {"minX": 16.828125, "minY": 148.875, "maxX": 45.6875, "maxY": 195.125}, "class_id": 2, "box_caption": "0 0.001", "scores": {"class_score": 0.0014123916625976562}, "domain": "pixel"}, {"position": {"minX": 16.859375, "minY": 84.875, "maxX": 45.6875, "maxY": 131.125}, "class_id": 2, "box_caption": "0 0.001", "scores": {"class_score": 0.0014123916625976562}, "domain": "pixel"}, {"position": {"minX": 16.8125, "minY": 116.875, "maxX": 45.6875, "maxY": 163.125}, "class_id": 2, "box_caption": "0 0.001", "scores": {"class_score": 0.0014123916625976562}, "domain": "pixel"}, {"position": {"minX": 61.125, "minY": 222.125, "maxX": 226.375, "maxY": 385.0}, "class_id": 0, "box_caption": "bus 0.001", "scores": {"class_score": 0.00141143798828125}, "domain": "pixel"}, {"position": {"minX": 233.875, "minY": 244.625, "maxX": 374.5, "maxY": 364.0}, "class_id": 0, "box_caption": "bus 0.001", "scores": {"class_score": 0.0014095306396484375}, "domain": "pixel"}, {"position": {"minX": 105.875, "minY": 244.75, "maxX": 246.625, "maxY": 363.75}, "class_id": 0, "box_caption": "bus 0.001", "scores": {"class_score": 0.0014095306396484375}, "domain": "pixel"}, {"position": {"minX": 169.625, "minY": 244.625, "maxX": 311.0, "maxY": 364.0}, "class_id": 0, "box_caption": "bus 0.001", "scores": {"class_score": 0.001407623291015625}, "domain": "pixel"}, {"position": {"minX": 16.21875, "minY": 229.625, "maxX": 45.9375, "maxY": 274.5}, "class_id": 2, "box_caption": "0 0.001", "scores": {"class_score": 0.001407623291015625}, "domain": "pixel"}, {"position": {"minX": 157.875, "minY": 126.375, "maxX": 321.5, "maxY": 288.5}, "class_id": 0, "box_caption": "bus 0.001", "scores": {"class_score": 0.0014019012451171875}, "domain": "pixel"}, {"position": {"minX": 9.0, "minY": 178.625, "maxX": 150.5, "maxY": 301.5}, "class_id": 0, "box_caption": "bus 0.001", "scores": {"class_score": 0.0014009475708007812}, "domain": "pixel"}, {"position": {"minX": 155.25, "minY": 31.375, "maxX": 326.75, "maxY": 191.125}, "class_id": 0, "box_caption": "bus 0.001", "scores": {"class_score": 0.001399993896484375}, "domain": "pixel"}, {"position": {"minX": 16.78125, "minY": 196.875, "maxX": 45.71875, "maxY": 243.125}, "class_id": 2, "box_caption": "0 0.001", "scores": {"class_score": 0.0013971328735351562}, "domain": "pixel"}, {"position": {"minX": 252.0, "minY": -1.0625, "maxX": 419.0, "maxY": 160.5}, "class_id": 0, "box_caption": "bus 0.001", "scores": {"class_score": 0.0013933181762695312}, "domain": "pixel"}, {"position": {"minX": -34.625, "minY": 159.0, "maxX": 130.0, "maxY": 320.0}, "class_id": 0, "box_caption": "bus 0.001", "scores": {"class_score": 0.0013828277587890625}, "domain": "pixel"}, {"position": {"minX": -34.375, "minY": 95.25, "maxX": 129.75, "maxY": 255.75}, "class_id": 0, "box_caption": "bus 0.001", "scores": {"class_score": 0.00138092041015625}, "domain": "pixel"}, {"position": {"minX": -34.375, "minY": 31.25, "maxX": 129.75, "maxY": 191.75}, "class_id": 0, "box_caption": "bus 0.001", "scores": {"class_score": 0.00138092041015625}, "domain": "pixel"}, {"position": {"minX": 157.875, "minY": 191.25, "maxX": 321.5, "maxY": 351.75}, "class_id": 0, "box_caption": "bus 0.001", "scores": {"class_score": 0.00138092041015625}, "domain": "pixel"}, {"position": {"minX": 319.0, "minY": -33.9375, "maxX": 481.0, "maxY": 129.0}, "class_id": 0, "box_caption": "bus 0.001", "scores": {"class_score": 0.0013761520385742188}, "domain": "pixel"}, {"position": {"minX": 189.25, "minY": -0.375, "maxX": 354.75, "maxY": 159.375}, "class_id": 0, "box_caption": "bus 0.001", "scores": {"class_score": 0.0013704299926757812}, "domain": "pixel"}, {"position": {"minX": 223.0, "minY": -33.4375, "maxX": 384.5, "maxY": 128.5}, "class_id": 0, "box_caption": "bus 0.001", "scores": {"class_score": 0.0013685226440429688}, "domain": "pixel"}, {"position": {"minX": 137.25, "minY": 277.75, "maxX": 278.75, "maxY": 396.25}, "class_id": 0, "box_caption": "bus 0.001", "scores": {"class_score": 0.0013675689697265625}, "domain": "pixel"}, {"position": {"minX": 201.25, "minY": 277.75, "maxX": 342.75, "maxY": 396.25}, "class_id": 0, "box_caption": "bus 0.001", "scores": {"class_score": 0.0013675689697265625}, "domain": "pixel"}, {"position": {"minX": 265.25, "minY": 277.75, "maxX": 406.75, "maxY": 396.25}, "class_id": 0, "box_caption": "bus 0.001", "scores": {"class_score": 0.0013675689697265625}, "domain": "pixel"}, {"position": {"minX": 73.25, "minY": 277.75, "maxX": 214.75, "maxY": 396.25}, "class_id": 0, "box_caption": "bus 0.001", "scores": {"class_score": 0.0013675689697265625}, "domain": "pixel"}, {"position": {"minX": 220.25, "minY": 128.0, "maxX": 387.25, "maxY": 287.5}, "class_id": 0, "box_caption": "bus 0.001", "scores": {"class_score": 0.0013647079467773438}, "domain": "pixel"}, {"position": {"minX": 9.375, "minY": 277.5, "maxX": 150.625, "maxY": 396.5}, "class_id": 0, "box_caption": "bus 0.001", "scores": {"class_score": 0.0013647079467773438}, "domain": "pixel"}, {"position": {"minX": -33.65625, "minY": -32.6875, "maxX": 129.125, "maxY": 127.9375}, "class_id": 0, "box_caption": "bus 0.001", "scores": {"class_score": 0.0013599395751953125}, "domain": "pixel"}, {"position": {"minX": -4.0, "minY": 191.25, "maxX": 163.75, "maxY": 351.75}, "class_id": 0, "box_caption": "bus 0.001", "scores": {"class_score": 0.0013370513916015625}, "domain": "pixel"}, {"position": {"minX": 16.328125, "minY": 21.953125, "maxX": 47.625, "maxY": 67.1875}, "class_id": 2, "box_caption": "0 0.001", "scores": {"class_score": 0.00133514404296875}, "domain": "pixel"}, {"position": {"minX": 264.5, "minY": 150.5, "maxX": 408.5, "maxY": 267.5}, "class_id": 0, "box_caption": "bus 0.001", "scores": {"class_score": 0.00133514404296875}, "domain": "pixel"}, {"position": {"minX": 14.0625, "minY": 38.0625, "maxX": 47.1875, "maxY": 82.4375}, "class_id": 2, "box_caption": "0 0.001", "scores": {"class_score": 0.0013322830200195312}, "domain": "pixel"}, {"position": {"minX": 195.25, "minY": -64.625, "maxX": 350.25, "maxY": 96.5}, "class_id": 0, "box_caption": "bus 0.001", "scores": {"class_score": 0.0013246536254882812}, "domain": "pixel"}, {"position": {"minX": 99.0625, "minY": -64.625, "maxX": 254.25, "maxY": 96.5}, "class_id": 0, "box_caption": "bus 0.001", "scores": {"class_score": 0.0013246536254882812}, "domain": "pixel"}, {"position": {"minX": 35.0625, "minY": -64.625, "maxX": 190.25, "maxY": 96.5}, "class_id": 0, "box_caption": "bus 0.001", "scores": {"class_score": 0.0013246536254882812}, "domain": "pixel"}, {"position": {"minX": 259.25, "minY": -64.75, "maxX": 414.25, "maxY": 96.5}, "class_id": 0, "box_caption": "bus 0.001", "scores": {"class_score": 0.0013246536254882812}, "domain": "pixel"}, {"position": {"minX": 16.328125, "minY": 21.953125, "maxX": 47.625, "maxY": 67.1875}, "class_id": 12, "box_caption": "- 0.001", "scores": {"class_score": 0.0013141632080078125}, "domain": "pixel"}, {"position": {"minX": 17.046875, "minY": 274.5, "maxX": 45.875, "maxY": 325.5}, "class_id": 12, "box_caption": "- 0.001", "scores": {"class_score": 0.0012998580932617188}, "domain": "pixel"}, {"position": {"minX": 16.90625, "minY": 244.25, "maxX": 45.84375, "maxY": 291.75}, "class_id": 12, "box_caption": "- 0.001", "scores": {"class_score": 0.0012531280517578125}, "domain": "pixel"}, {"position": {"minX": 73.5, "minY": 6.625, "maxX": 278.75, "maxY": 214.625}, "class_id": 0, "box_caption": "bus 0.001", "scores": {"class_score": 0.0012359619140625}, "domain": "pixel"}, {"position": {"minX": 16.765625, "minY": 212.5, "maxX": 45.875, "maxY": 259.5}, "class_id": 12, "box_caption": "- 0.001", "scores": {"class_score": 0.0012273788452148438}, "domain": "pixel"}, {"position": {"minX": 15.7265625, "minY": 261.5, "maxX": 46.5, "maxY": 306.0}, "class_id": 12, "box_caption": "- 0.001", "scores": {"class_score": 0.001216888427734375}, "domain": "pixel"}, {"position": {"minX": 16.84375, "minY": 181.0, "maxX": 45.6875, "maxY": 227.0}, "class_id": 12, "box_caption": "- 0.001", "scores": {"class_score": 0.0011997222900390625}, "domain": "pixel"}, {"position": {"minX": 328.5, "minY": 166.25, "maxX": 536.0, "maxY": 377.75}, "class_id": 0, "box_caption": "bus 0.001", "scores": {"class_score": 0.0011997222900390625}, "domain": "pixel"}, {"position": {"minX": 328.0, "minY": 6.4375, "maxX": 536.5, "maxY": 217.25}, "class_id": 0, "box_caption": "bus 0.001", "scores": {"class_score": 0.0011997222900390625}, "domain": "pixel"}, {"position": {"minX": 328.0, "minY": 102.5625, "maxX": 537.0, "maxY": 313.25}, "class_id": 0, "box_caption": "bus 0.001", "scores": {"class_score": 0.0011997222900390625}, "domain": "pixel"}, {"position": {"minX": 16.796875, "minY": 68.875, "maxX": 45.6875, "maxY": 115.125}, "class_id": 12, "box_caption": "- 0.001", "scores": {"class_score": 0.00119781494140625}, "domain": "pixel"}, {"position": {"minX": 16.609375, "minY": 52.90625, "maxX": 45.6875, "maxY": 99.0}, "class_id": 12, "box_caption": "- 0.001", "scores": {"class_score": 0.0011959075927734375}, "domain": "pixel"}, {"position": {"minX": 16.828125, "minY": 164.875, "maxX": 45.6875, "maxY": 211.125}, "class_id": 12, "box_caption": "- 0.001", "scores": {"class_score": 0.0011949539184570312}, "domain": "pixel"}, {"position": {"minX": 16.8125, "minY": 116.875, "maxX": 45.6875, "maxY": 163.125}, "class_id": 12, "box_caption": "- 0.001", "scores": {"class_score": 0.0011949539184570312}, "domain": "pixel"}, {"position": {"minX": 16.84375, "minY": 100.875, "maxX": 45.6875, "maxY": 147.125}, "class_id": 12, "box_caption": "- 0.001", "scores": {"class_score": 0.0011949539184570312}, "domain": "pixel"}, {"position": {"minX": 16.859375, "minY": 84.875, "maxX": 45.6875, "maxY": 131.125}, "class_id": 12, "box_caption": "- 0.001", "scores": {"class_score": 0.0011949539184570312}, "domain": "pixel"}, {"position": {"minX": 16.828125, "minY": 148.875, "maxX": 45.6875, "maxY": 195.125}, "class_id": 12, "box_caption": "- 0.001", "scores": {"class_score": 0.0011949539184570312}, "domain": "pixel"}, {"position": {"minX": 16.828125, "minY": 132.875, "maxX": 45.6875, "maxY": 179.125}, "class_id": 12, "box_caption": "- 0.001", "scores": {"class_score": 0.0011949539184570312}, "domain": "pixel"}, {"position": {"minX": 16.78125, "minY": 196.875, "maxX": 45.71875, "maxY": 243.125}, "class_id": 12, "box_caption": "- 0.001", "scores": {"class_score": 0.001190185546875}, "domain": "pixel"}, {"position": {"minX": 299.5, "minY": 135.0, "maxX": 502.5, "maxY": 345.5}, "class_id": 0, "box_caption": "bus 0.001", "scores": {"class_score": 0.0011873245239257812}, "domain": "pixel"}, {"position": {"minX": -96.375, "minY": -86.375, "maxX": 129.125, "maxY": 117.0}, "class_id": 0, "box_caption": "bus 0.001", "scores": {"class_score": 0.0011873245239257812}, "domain": "pixel"}, {"position": {"minX": 298.5, "minY": 39.625, "maxX": 503.5, "maxY": 248.625}, "class_id": 0, "box_caption": "bus 0.001", "scores": {"class_score": 0.0011873245239257812}, "domain": "pixel"}, {"position": {"minX": 299.5, "minY": -24.9375, "maxX": 502.5, "maxY": 185.25}, "class_id": 0, "box_caption": "bus 0.001", "scores": {"class_score": 0.0011873245239257812}, "domain": "pixel"}, {"position": {"minX": 170.0, "minY": 8.6875, "maxX": 376.5, "maxY": 215.0}, "class_id": 0, "box_caption": "bus 0.001", "scores": {"class_score": 0.0011854171752929688}, "domain": "pixel"}, {"position": {"minX": 8.25, "minY": 8.0625, "maxX": 217.5, "maxY": 215.75}, "class_id": 0, "box_caption": "bus 0.001", "scores": {"class_score": 0.0011854171752929688}, "domain": "pixel"}, {"position": {"minX": 10.0, "minY": 103.3125, "maxX": 215.75, "maxY": 312.75}, "class_id": 0, "box_caption": "bus 0.001", "scores": {"class_score": 0.0011854171752929688}, "domain": "pixel"}, {"position": {"minX": -89.125, "minY": 229.5, "maxX": 121.75, "maxY": 441.0}, "class_id": 0, "box_caption": "bus 0.001", "scores": {"class_score": 0.0011854171752929688}, "domain": "pixel"}, {"position": {"minX": -21.0625, "minY": 39.4375, "maxX": 183.25, "maxY": 248.75}, "class_id": 0, "box_caption": "bus 0.001", "scores": {"class_score": 0.0011835098266601562}, "domain": "pixel"}, {"position": {"minX": 323.0, "minY": -55.375, "maxX": 541.5, "maxY": 150.625}, "class_id": 0, "box_caption": "bus 0.001", "scores": {"class_score": 0.0011835098266601562}, "domain": "pixel"}, {"position": {"minX": 233.75, "minY": 167.0, "maxX": 440.25, "maxY": 377.0}, "class_id": 0, "box_caption": "bus 0.001", "scores": {"class_score": 0.0011835098266601562}, "domain": "pixel"}, {"position": {"minX": 126.125, "minY": -85.875, "maxX": 355.0, "maxY": 116.625}, "class_id": 0, "box_caption": "bus 0.001", "scores": {"class_score": 0.00118255615234375}, "domain": "pixel"}, {"position": {"minX": 16.21875, "minY": 229.625, "maxX": 45.9375, "maxY": 274.5}, "class_id": 12, "box_caption": "- 0.001", "scores": {"class_score": 0.0011816024780273438}, "domain": "pixel"}, {"position": {"minX": 198.75, "minY": 72.625, "maxX": 411.25, "maxY": 279.0}, "class_id": 0, "box_caption": "bus 0.001", "scores": {"class_score": 0.0011816024780273438}, "domain": "pixel"}, {"position": {"minX": 170.625, "minY": 167.125, "maxX": 375.5, "maxY": 377.0}, "class_id": 0, "box_caption": "bus 0.001", "scores": {"class_score": 0.0011806488037109375}, "domain": "pixel"}, {"position": {"minX": 106.0, "minY": 104.375, "maxX": 312.5, "maxY": 311.0}, "class_id": 0, "box_caption": "bus 0.001", "scores": {"class_score": 0.001178741455078125}, "domain": "pixel"}, {"position": {"minX": 39.125, "minY": 71.9375, "maxX": 250.375, "maxY": 279.5}, "class_id": 0, "box_caption": "bus 0.001", "scores": {"class_score": 0.001178741455078125}, "domain": "pixel"}, {"position": {"minX": 231.0, "minY": 40.125, "maxX": 442.5, "maxY": 247.375}, "class_id": 0, "box_caption": "bus 0.001", "scores": {"class_score": 0.0011777877807617188}, "domain": "pixel"}, {"position": {"minX": 202.5, "minY": -24.375, "maxX": 407.5, "maxY": 184.625}, "class_id": 0, "box_caption": "bus 0.001", "scores": {"class_score": 0.0011768341064453125}, "domain": "pixel"}, {"position": {"minX": -85.625, "minY": 136.125, "maxX": 120.125, "maxY": 344.0}, "class_id": 0, "box_caption": "bus 0.001", "scores": {"class_score": 0.0011758804321289062}, "domain": "pixel"}, {"position": {"minX": -85.5, "minY": 8.125, "maxX": 120.0, "maxY": 215.875}, "class_id": 0, "box_caption": "bus 0.001", "scores": {"class_score": 0.0011758804321289062}, "domain": "pixel"}, {"position": {"minX": -85.5, "minY": 72.125, "maxX": 120.0, "maxY": 280.0}, "class_id": 0, "box_caption": "bus 0.001", "scores": {"class_score": 0.0011758804321289062}, "domain": "pixel"}, {"position": {"minX": 101.25, "minY": -54.5, "maxX": 316.5, "maxY": 150.0}, "class_id": 0, "box_caption": "bus 0.001", "scores": {"class_score": 0.0011758804321289062}, "domain": "pixel"}, {"position": {"minX": 43.625, "minY": 134.25, "maxX": 246.125, "maxY": 346.0}, "class_id": 0, "box_caption": "bus 0.001", "scores": {"class_score": 0.0011758804321289062}, "domain": "pixel"}, {"position": {"minX": 62.6875, "minY": -86.25, "maxX": 290.25, "maxY": 117.125}, "class_id": 0, "box_caption": "bus 0.001", "scores": {"class_score": 0.0011758804321289062}, "domain": "pixel"}, {"position": {"minX": -33.3125, "minY": -86.25, "maxX": 194.25, "maxY": 117.125}, "class_id": 0, "box_caption": "bus 0.001", "scores": {"class_score": 0.0011758804321289062}, "domain": "pixel"}, {"position": {"minX": -28.5625, "minY": 202.5, "maxX": 190.25, "maxY": 404.5}, "class_id": 0, "box_caption": "bus 0.001", "scores": {"class_score": 0.0011758804321289062}, "domain": "pixel"}, {"position": {"minX": 222.75, "minY": -86.25, "maxX": 450.25, "maxY": 117.125}, "class_id": 0, "box_caption": "bus 0.001", "scores": {"class_score": 0.0011758804321289062}, "domain": "pixel"}, {"position": {"minX": 286.0, "minY": -86.3125, "maxX": 515.0, "maxY": 117.0625}, "class_id": 0, "box_caption": "bus 0.001", "scores": {"class_score": 0.0011758804321289062}, "domain": "pixel"}, {"position": {"minX": 200.875, "minY": 136.125, "maxX": 409.5, "maxY": 344.0}, "class_id": 0, "box_caption": "bus 0.001", "scores": {"class_score": 0.0011749267578125}, "domain": "pixel"}, {"position": {"minX": 105.6875, "minY": 41.25, "maxX": 312.75, "maxY": 246.25}, "class_id": 0, "box_caption": "bus 0.001", "scores": {"class_score": 0.0011749267578125}, "domain": "pixel"}, {"position": {"minX": 39.75, "minY": -54.8125, "maxX": 250.5, "maxY": 150.75}, "class_id": 0, "box_caption": "bus 0.001", "scores": {"class_score": 0.0011730194091796875}, "domain": "pixel"}, {"position": {"minX": 263.5, "minY": -55.0, "maxX": 474.5, "maxY": 150.875}, "class_id": 0, "box_caption": "bus 0.001", "scores": {"class_score": 0.0011730194091796875}, "domain": "pixel"}, {"position": {"minX": 169.25, "minY": -54.96875, "maxX": 377.25, "maxY": 151.0}, "class_id": 0, "box_caption": "bus 0.001", "scores": {"class_score": 0.0011720657348632812}, "domain": "pixel"}, {"position": {"minX": -53.0625, "minY": -23.625, "maxX": 151.75, "maxY": 184.0}, "class_id": 0, "box_caption": "bus 0.001", "scores": {"class_score": 0.0011720657348632812}, "domain": "pixel"}, {"position": {"minX": 137.75, "minY": 198.875, "maxX": 344.25, "maxY": 409.0}, "class_id": 0, "box_caption": "bus 0.001", "scores": {"class_score": 0.0011720657348632812}, "domain": "pixel"}, {"position": {"minX": 202.125, "minY": 198.5, "maxX": 408.0, "maxY": 409.5}, "class_id": 0, "box_caption": "bus 0.001", "scores": {"class_score": 0.0011720657348632812}, "domain": "pixel"}, {"position": {"minX": 265.25, "minY": 8.625, "maxX": 473.25, "maxY": 215.125}, "class_id": 0, "box_caption": "bus 0.001", "scores": {"class_score": 0.0011720657348632812}, "domain": "pixel"}, {"position": {"minX": 103.625, "minY": 149.125, "maxX": 245.625, "maxY": 268.0}, "class_id": 1, "box_caption": "panel 0.001", "scores": {"class_score": 0.001171112060546875}, "domain": "pixel"}, {"position": {"minX": 11.1875, "minY": 168.75, "maxX": 215.5, "maxY": 375.75}, "class_id": 0, "box_caption": "bus 0.001", "scores": {"class_score": 0.0011701583862304688}, "domain": "pixel"}, {"position": {"minX": 139.5, "minY": 135.75, "maxX": 343.0, "maxY": 344.75}, "class_id": 0, "box_caption": "bus 0.001", "scores": {"class_score": 0.0011701583862304688}, "domain": "pixel"}, {"position": {"minX": 102.375, "minY": 53.75, "maxX": 246.875, "maxY": 171.25}, "class_id": 1, "box_caption": "panel 0.001", "scores": {"class_score": 0.0011692047119140625}, "domain": "pixel"}, {"position": {"minX": -53.0625, "minY": 104.3125, "maxX": 151.75, "maxY": 312.0}, "class_id": 0, "box_caption": "bus 0.001", "scores": {"class_score": 0.0011692047119140625}, "domain": "pixel"}, {"position": {"minX": 267.0, "minY": 198.75, "maxX": 471.0, "maxY": 409.25}, "class_id": 0, "box_caption": "bus 0.001", "scores": {"class_score": 0.0011692047119140625}, "domain": "pixel"}, {"position": {"minX": 74.0, "minY": 198.5, "maxX": 280.0, "maxY": 409.5}, "class_id": 0, "box_caption": "bus 0.001", "scores": {"class_score": 0.0011682510375976562}, "domain": "pixel"}, {"position": {"minX": 170.125, "minY": 103.9375, "maxX": 375.0, "maxY": 311.5}, "class_id": 0, "box_caption": "bus 0.001", "scores": {"class_score": 0.0011653900146484375}, "domain": "pixel"}, {"position": {"minX": 137.25, "minY": 72.75, "maxX": 345.25, "maxY": 279.25}, "class_id": 0, "box_caption": "bus 0.001", "scores": {"class_score": 0.0011653900146484375}, "domain": "pixel"}, {"position": {"minX": 109.0, "minY": 166.25, "maxX": 308.75, "maxY": 377.75}, "class_id": 0, "box_caption": "bus 0.001", "scores": {"class_score": 0.0011644363403320312}, "domain": "pixel"}, {"position": {"minX": 261.5, "minY": 72.75, "maxX": 476.0, "maxY": 278.25}, "class_id": 0, "box_caption": "bus 0.001", "scores": {"class_score": 0.0011644363403320312}, "domain": "pixel"}, {"position": {"minX": 103.0, "minY": 117.875, "maxX": 246.5, "maxY": 235.125}, "class_id": 1, "box_caption": "panel 0.001", "scores": {"class_score": 0.0011644363403320312}, "domain": "pixel"}, {"position": {"minX": -19.5625, "minY": 135.125, "maxX": 182.0, "maxY": 345.0}, "class_id": 0, "box_caption": "bus 0.001", "scores": {"class_score": 0.0011606216430664062}, "domain": "pixel"}, {"position": {"minX": -52.84375, "minY": 168.375, "maxX": 151.25, "maxY": 376.0}, "class_id": 0, "box_caption": "bus 0.001", "scores": {"class_score": 0.0011587142944335938}, "domain": "pixel"}, {"position": {"minX": 78.6875, "minY": 239.375, "maxX": 107.4375, "maxY": 267.75}, "class_id": 2, "box_caption": "0 0.001", "scores": {"class_score": 0.0011491775512695312}, "domain": "pixel"}, {"position": {"minX": 103.875, "minY": 228.0, "maxX": 312.5, "maxY": 443.0}, "class_id": 0, "box_caption": "bus 0.001", "scores": {"class_score": 0.0011472702026367188}, "domain": "pixel"}, {"position": {"minX": 39.875, "minY": 227.875, "maxX": 248.375, "maxY": 443.0}, "class_id": 0, "box_caption": "bus 0.001", "scores": {"class_score": 0.0011472702026367188}, "domain": "pixel"}, {"position": {"minX": 231.625, "minY": 228.0, "maxX": 440.5, "maxY": 443.0}, "class_id": 0, "box_caption": "bus 0.001", "scores": {"class_score": 0.0011472702026367188}, "domain": "pixel"}, {"position": {"minX": 167.75, "minY": 228.0, "maxX": 376.25, "maxY": 443.0}, "class_id": 0, "box_caption": "bus 0.001", "scores": {"class_score": 0.0011472702026367188}, "domain": "pixel"}, {"position": {"minX": 103.5, "minY": 181.625, "maxX": 246.5, "maxY": 299.25}, "class_id": 1, "box_caption": "panel 0.001", "scores": {"class_score": 0.0011472702026367188}, "domain": "pixel"}, {"position": {"minX": 363.0, "minY": 118.375, "maxX": 501.0, "maxY": 233.625}, "class_id": 1, "box_caption": "panel 0.001", "scores": {"class_score": 0.0011453628540039062}, "domain": "pixel"}, {"position": {"minX": 229.25, "minY": 100.4375, "maxX": 443.25, "maxY": 314.0}, "class_id": 0, "box_caption": "bus 0.001", "scores": {"class_score": 0.0011415481567382812}, "domain": "pixel"}, {"position": {"minX": 363.0, "minY": 246.25, "maxX": 501.0, "maxY": 361.75}, "class_id": 1, "box_caption": "panel 0.001", "scores": {"class_score": 0.001140594482421875}, "domain": "pixel"}, {"position": {"minX": 363.25, "minY": 182.5, "maxX": 501.25, "maxY": 297.5}, "class_id": 1, "box_caption": "panel 0.001", "scores": {"class_score": 0.0011396408081054688}, "domain": "pixel"}, {"position": {"minX": 363.0, "minY": 86.625, "maxX": 501.5, "maxY": 201.375}, "class_id": 1, "box_caption": "panel 0.001", "scores": {"class_score": 0.0011396408081054688}, "domain": "pixel"}, {"position": {"minX": 363.0, "minY": 150.75, "maxX": 501.5, "maxY": 265.25}, "class_id": 1, "box_caption": "panel 0.001", "scores": {"class_score": 0.0011396408081054688}, "domain": "pixel"}, {"position": {"minX": 102.375, "minY": 86.625, "maxX": 247.125, "maxY": 202.875}, "class_id": 1, "box_caption": "panel 0.001", "scores": {"class_score": 0.0011386871337890625}, "domain": "pixel"}, {"position": {"minX": 363.25, "minY": 22.5625, "maxX": 501.25, "maxY": 137.5}, "class_id": 1, "box_caption": "panel 0.001", "scores": {"class_score": 0.0011377334594726562}, "domain": "pixel"}, {"position": {"minX": 363.25, "minY": 214.5, "maxX": 501.25, "maxY": 329.5}, "class_id": 1, "box_caption": "panel 0.001", "scores": {"class_score": 0.0011377334594726562}, "domain": "pixel"}, {"position": {"minX": 363.0, "minY": 54.5625, "maxX": 501.5, "maxY": 169.5}, "class_id": 1, "box_caption": "panel 0.001", "scores": {"class_score": 0.00113677978515625}, "domain": "pixel"}, {"position": {"minX": 330.75, "minY": 114.9375, "maxX": 467.75, "maxY": 236.25}, "class_id": 1, "box_caption": "panel 0.001", "scores": {"class_score": 0.0011320114135742188}, "domain": "pixel"}, {"position": {"minX": 138.5, "minY": 19.5, "maxX": 276.5, "maxY": 140.25}, "class_id": 1, "box_caption": "panel 0.001", "scores": {"class_score": 0.0011234283447265625}, "domain": "pixel"}, {"position": {"minX": 169.875, "minY": 49.0625, "maxX": 307.5, "maxY": 175.25}, "class_id": 1, "box_caption": "panel 0.001", "scores": {"class_score": 0.0011224746704101562}, "domain": "pixel"}, {"position": {"minX": 360.5, "minY": 276.0, "maxX": 501.5, "maxY": 397.0}, "class_id": 1, "box_caption": "panel 0.001", "scores": {"class_score": 0.00112152099609375}, "domain": "pixel"}, {"position": {"minX": 42.75, "minY": 83.0, "maxX": 180.0, "maxY": 204.75}, "class_id": 1, "box_caption": "panel 0.001", "scores": {"class_score": 0.0011205673217773438}, "domain": "pixel"}, {"position": {"minX": 342.0, "minY": 255.5, "maxX": 523.5, "maxY": 416.5}, "class_id": 2, "box_caption": "0 0.001", "scores": {"class_score": 0.0011138916015625}, "domain": "pixel"}, {"position": {"minX": 362.0, "minY": -7.375, "maxX": 503.5, "maxY": 104.1875}, "class_id": 1, "box_caption": "panel 0.001", "scores": {"class_score": 0.0011138916015625}, "domain": "pixel"}, {"position": {"minX": 42.1875, "minY": 179.25, "maxX": 181.25, "maxY": 300.5}, "class_id": 1, "box_caption": "panel 0.001", "scores": {"class_score": 0.0011129379272460938}, "domain": "pixel"}, {"position": {"minX": 201.0, "minY": 148.875, "maxX": 341.5, "maxY": 267.5}, "class_id": 1, "box_caption": "panel 0.001", "scores": {"class_score": 0.0011110305786132812}, "domain": "pixel"}, {"position": {"minX": 200.25, "minY": 117.3125, "maxX": 342.75, "maxY": 235.25}, "class_id": 1, "box_caption": "panel 0.001", "scores": {"class_score": 0.0011110305786132812}, "domain": "pixel"}, {"position": {"minX": 42.8125, "minY": 149.375, "maxX": 181.75, "maxY": 266.75}, "class_id": 1, "box_caption": "panel 0.001", "scores": {"class_score": 0.001110076904296875}, "domain": "pixel"}, {"position": {"minX": 297.5, "minY": 84.375, "maxX": 438.5, "maxY": 203.625}, "class_id": 1, "box_caption": "panel 0.001", "scores": {"class_score": 0.0011072158813476562}, "domain": "pixel"}, {"position": {"minX": 266.25, "minY": 213.125, "maxX": 406.25, "maxY": 330.75}, "class_id": 1, "box_caption": "panel 0.001", "scores": {"class_score": 0.0011072158813476562}, "domain": "pixel"}, {"position": {"minX": 318.0, "minY": 189.0, "maxX": 482.0, "maxY": 353.5}, "class_id": 1, "box_caption": "panel 0.001", "scores": {"class_score": 0.0011053085327148438}, "domain": "pixel"}, {"position": {"minX": 138.0, "minY": 211.5, "maxX": 277.5, "maxY": 332.0}, "class_id": 1, "box_caption": "panel 0.001", "scores": {"class_score": 0.0011043548583984375}, "domain": "pixel"}, {"position": {"minX": 297.5, "minY": 148.25, "maxX": 438.0, "maxY": 268.0}, "class_id": 1, "box_caption": "panel 0.001", "scores": {"class_score": 0.0011043548583984375}, "domain": "pixel"}, {"position": {"minX": 348.75, "minY": 219.625, "maxX": 515.0, "maxY": 387.5}, "class_id": 1, "box_caption": "panel 0.001", "scores": {"class_score": 0.0011043548583984375}, "domain": "pixel"}, {"position": {"minX": 42.5, "minY": 20.6875, "maxX": 182.0, "maxY": 139.25}, "class_id": 1, "box_caption": "panel 0.001", "scores": {"class_score": 0.0011034011840820312}, "domain": "pixel"}, {"position": {"minX": 10.5, "minY": 52.6875, "maxX": 150.0, "maxY": 171.25}, "class_id": 1, "box_caption": "panel 0.001", "scores": {"class_score": 0.0011034011840820312}, "domain": "pixel"}, {"position": {"minX": 202.375, "minY": 212.75, "maxX": 342.0, "maxY": 331.25}, "class_id": 1, "box_caption": "panel 0.001", "scores": {"class_score": 0.0011034011840820312}, "domain": "pixel"}, {"position": {"minX": 318.0, "minY": -2.8125, "maxX": 482.0, "maxY": 161.25}, "class_id": 1, "box_caption": "panel 0.001", "scores": {"class_score": 0.001102447509765625}, "domain": "pixel"}, {"position": {"minX": 318.0, "minY": 61.8125, "maxX": 481.5, "maxY": 225.0}, "class_id": 1, "box_caption": "panel 0.001", "scores": {"class_score": 0.0011005401611328125}, "domain": "pixel"}, {"position": {"minX": 298.5, "minY": 180.75, "maxX": 438.0, "maxY": 299.25}, "class_id": 1, "box_caption": "panel 0.001", "scores": {"class_score": 0.0011005401611328125}, "domain": "pixel"}, {"position": {"minX": 10.4375, "minY": 116.875, "maxX": 150.25, "maxY": 235.125}, "class_id": 1, "box_caption": "panel 0.001", "scores": {"class_score": 0.0011005401611328125}, "domain": "pixel"}, {"position": {"minX": 361.5, "minY": -36.75, "maxX": 504.5, "maxY": 70.5625}, "class_id": 1, "box_caption": "panel 0.001", "scores": {"class_score": 0.0010995864868164062}, "domain": "pixel"}, {"position": {"minX": 74.25, "minY": 212.0, "maxX": 213.75, "maxY": 332.0}, "class_id": 1, "box_caption": "panel 0.001", "scores": {"class_score": 0.0010986328125}, "domain": "pixel"}, {"position": {"minX": 199.25, "minY": 52.125, "maxX": 344.75, "maxY": 172.0}, "class_id": 1, "box_caption": "panel 0.001", "scores": {"class_score": 0.0010976791381835938}, "domain": "pixel"}, {"position": {"minX": -1.9375, "minY": -2.5, "maxX": 161.5, "maxY": 161.125}, "class_id": 1, "box_caption": "panel 0.001", "scores": {"class_score": 0.0010967254638671875}, "domain": "pixel"}, {"position": {"minX": 222.25, "minY": 190.25, "maxX": 385.25, "maxY": 352.75}, "class_id": 1, "box_caption": "panel 0.001", "scores": {"class_score": 0.0010967254638671875}, "domain": "pixel"}, {"position": {"minX": 157.875, "minY": 126.375, "maxX": 321.5, "maxY": 288.5}, "class_id": 1, "box_caption": "panel 0.001", "scores": {"class_score": 0.0010957717895507812}, "domain": "pixel"}, {"position": {"minX": 189.25, "minY": -0.375, "maxX": 354.75, "maxY": 159.375}, "class_id": 1, "box_caption": "panel 0.001", "scores": {"class_score": 0.0010957717895507812}, "domain": "pixel"}, {"position": {"minX": -1.9375, "minY": 61.875, "maxX": 161.5, "maxY": 224.875}, "class_id": 1, "box_caption": "panel 0.001", "scores": {"class_score": 0.0010957717895507812}, "domain": "pixel"}, {"position": {"minX": 202.125, "minY": 180.875, "maxX": 343.0, "maxY": 299.25}, "class_id": 1, "box_caption": "panel 0.001", "scores": {"class_score": 0.001094818115234375}, "domain": "pixel"}, {"position": {"minX": -66.875, "minY": 224.625, "maxX": 98.375, "maxY": 383.5}, "class_id": 1, "box_caption": "panel 0.001", "scores": {"class_score": 0.001094818115234375}, "domain": "pixel"}, {"position": {"minX": 233.875, "minY": 83.875, "maxX": 374.0, "maxY": 204.125}, "class_id": 1, "box_caption": "panel 0.001", "scores": {"class_score": 0.001094818115234375}, "domain": "pixel"}, {"position": {"minX": 349.25, "minY": 155.625, "maxX": 515.0, "maxY": 323.0}, "class_id": 1, "box_caption": "panel 0.001", "scores": {"class_score": 0.001094818115234375}, "domain": "pixel"}, {"position": {"minX": 317.25, "minY": 127.375, "maxX": 482.25, "maxY": 288.0}, "class_id": 1, "box_caption": "panel 0.001", "scores": {"class_score": 0.001094818115234375}, "domain": "pixel"}, {"position": {"minX": 396.5, "minY": 5.734375, "maxX": 429.5, "maxY": 53.0}, "class_id": 1, "box_caption": "panel 0.001", "scores": {"class_score": 0.0010938644409179688}, "domain": "pixel"}, {"position": {"minX": 298.0, "minY": 20.15625, "maxX": 438.5, "maxY": 139.875}, "class_id": 1, "box_caption": "panel 0.001", "scores": {"class_score": 0.0010929107666015625}, "domain": "pixel"}, {"position": {"minX": 234.125, "minY": 20.53125, "maxX": 374.5, "maxY": 139.5}, "class_id": 1, "box_caption": "panel 0.001", "scores": {"class_score": 0.0010929107666015625}, "domain": "pixel"}, {"position": {"minX": 30.625, "minY": 93.8125, "maxX": 193.0, "maxY": 257.0}, "class_id": 1, "box_caption": "panel 0.001", "scores": {"class_score": 0.0010919570922851562}, "domain": "pixel"}, {"position": {"minX": 349.0, "minY": 91.875, "maxX": 515.0, "maxY": 259.0}, "class_id": 1, "box_caption": "panel 0.001", "scores": {"class_score": 0.0010919570922851562}, "domain": "pixel"}, {"position": {"minX": 62.0, "minY": -2.625, "maxX": 225.5, "maxY": 161.25}, "class_id": 1, "box_caption": "panel 0.001", "scores": {"class_score": 0.0010919570922851562}, "domain": "pixel"}, {"position": {"minX": 170.125, "minY": 82.375, "maxX": 309.0, "maxY": 205.625}, "class_id": 1, "box_caption": "panel 0.001", "scores": {"class_score": 0.0010919570922851562}, "domain": "pixel"}, {"position": {"minX": -1.75, "minY": 125.0625, "maxX": 161.375, "maxY": 289.5}, "class_id": 1, "box_caption": "panel 0.001", "scores": {"class_score": 0.0010919570922851562}, "domain": "pixel"}, {"position": {"minX": -66.5625, "minY": 96.125, "maxX": 98.0625, "maxY": 255.625}, "class_id": 1, "box_caption": "panel 0.001", "scores": {"class_score": 0.00109100341796875}, "domain": "pixel"}, {"position": {"minX": -66.625, "minY": 160.125, "maxX": 98.0, "maxY": 319.5}, "class_id": 1, "box_caption": "panel 0.001", "scores": {"class_score": 0.00109100341796875}, "domain": "pixel"}, {"position": {"minX": 29.6875, "minY": 191.5, "maxX": 193.75, "maxY": 351.5}, "class_id": 1, "box_caption": "panel 0.001", "scores": {"class_score": 0.00109100341796875}, "domain": "pixel"}, {"position": {"minX": -66.5625, "minY": 0.0625, "maxX": 98.0625, "maxY": 159.5}, "class_id": 1, "box_caption": "panel 0.001", "scores": {"class_score": 0.00109100341796875}, "domain": "pixel"}, {"position": {"minX": 349.0, "minY": 27.875, "maxX": 515.0, "maxY": 195.0}, "class_id": 1, "box_caption": "panel 0.001", "scores": {"class_score": 0.0010900497436523438}, "domain": "pixel"}, {"position": {"minX": -34.375, "minY": 31.25, "maxX": 129.75, "maxY": 191.75}, "class_id": 1, "box_caption": "panel 0.001", "scores": {"class_score": 0.0010890960693359375}, "domain": "pixel"}, {"position": {"minX": 125.0625, "minY": 159.75, "maxX": 291.0, "maxY": 319.25}, "class_id": 1, "box_caption": "panel 0.001", "scores": {"class_score": 0.0010890960693359375}, "domain": "pixel"}, {"position": {"minX": 201.75, "minY": 244.625, "maxX": 342.75, "maxY": 364.0}, "class_id": 1, "box_caption": "panel 0.001", "scores": {"class_score": 0.0010881423950195312}, "domain": "pixel"}, {"position": {"minX": 188.625, "minY": 64.5, "maxX": 355.0, "maxY": 222.75}, "class_id": 1, "box_caption": "panel 0.001", "scores": {"class_score": 0.0010881423950195312}, "domain": "pixel"}, {"position": {"minX": 265.75, "minY": 244.625, "maxX": 406.75, "maxY": 364.0}, "class_id": 1, "box_caption": "panel 0.001", "scores": {"class_score": 0.0010881423950195312}, "domain": "pixel"}, {"position": {"minX": 62.25, "minY": 156.625, "maxX": 225.75, "maxY": 321.5}, "class_id": 1, "box_caption": "panel 0.001", "scores": {"class_score": 0.0010881423950195312}, "domain": "pixel"}, {"position": {"minX": 264.5, "minY": 115.875, "maxX": 406.0, "maxY": 236.875}, "class_id": 1, "box_caption": "panel 0.001", "scores": {"class_score": 0.0010881423950195312}, "domain": "pixel"}, {"position": {"minX": 169.125, "minY": -37.15625, "maxX": 313.0, "maxY": 70.875}, "class_id": 1, "box_caption": "panel 0.001", "scores": {"class_score": 0.001087188720703125}, "domain": "pixel"}, {"position": {"minX": 158.25, "minY": -34.0, "maxX": 321.75, "maxY": 129.125}, "class_id": 1, "box_caption": "panel 0.001", "scores": {"class_score": 0.001087188720703125}, "domain": "pixel"}, {"position": {"minX": -56.3125, "minY": -38.59375, "maxX": 89.6875, "maxY": 71.75}, "class_id": 7, "box_caption": "5 0.001", "scores": {"class_score": 0.001087188720703125}, "domain": "pixel"}, {"position": {"minX": 233.375, "minY": -37.15625, "maxX": 376.5, "maxY": 70.875}, "class_id": 1, "box_caption": "panel 0.001", "scores": {"class_score": 0.001087188720703125}, "domain": "pixel"}, {"position": {"minX": 73.75, "minY": 244.625, "maxX": 214.75, "maxY": 364.0}, "class_id": 1, "box_caption": "panel 0.001", "scores": {"class_score": 0.0010862350463867188}, "domain": "pixel"}, {"position": {"minX": 254.375, "minY": 158.5, "maxX": 417.0, "maxY": 320.5}, "class_id": 1, "box_caption": "panel 0.001", "scores": {"class_score": 0.0010852813720703125}, "domain": "pixel"}, {"position": {"minX": -56.1875, "minY": 148.125, "maxX": 88.5625, "maxY": 267.75}, "class_id": 1, "box_caption": "panel 0.001", "scores": {"class_score": 0.0010852813720703125}, "domain": "pixel"}, {"position": {"minX": 138.125, "minY": -8.84375, "maxX": 279.5, "maxY": 105.5}, "class_id": 1, "box_caption": "panel 0.001", "scores": {"class_score": 0.0010843276977539062}, "domain": "pixel"}, {"position": {"minX": -22.46875, "minY": 20.1875, "maxX": 119.0, "maxY": 140.0}, "class_id": 1, "box_caption": "panel 0.001", "scores": {"class_score": 0.0010843276977539062}, "domain": "pixel"}, {"position": {"minX": 9.375, "minY": -37.15625, "maxX": 152.625, "maxY": 70.875}, "class_id": 1, "box_caption": "panel 0.001", "scores": {"class_score": 0.0010843276977539062}, "domain": "pixel"}, {"position": {"minX": 297.5, "minY": -37.15625, "maxX": 440.5, "maxY": 70.875}, "class_id": 1, "box_caption": "panel 0.001", "scores": {"class_score": 0.0010843276977539062}, "domain": "pixel"}, {"position": {"minX": 73.375, "minY": -37.15625, "maxX": 216.625, "maxY": 70.875}, "class_id": 1, "box_caption": "panel 0.001", "scores": {"class_score": 0.0010843276977539062}, "domain": "pixel"}, {"position": {"minX": 157.875, "minY": 191.25, "maxX": 321.5, "maxY": 351.75}, "class_id": 1, "box_caption": "panel 0.001", "scores": {"class_score": 0.0010843276977539062}, "domain": "pixel"}, {"position": {"minX": 137.625, "minY": 244.375, "maxX": 278.5, "maxY": 364.0}, "class_id": 1, "box_caption": "panel 0.001", "scores": {"class_score": 0.0010843276977539062}, "domain": "pixel"}, {"position": {"minX": 154.875, "minY": -2.375, "maxX": 327.0, "maxY": 161.125}, "class_id": 2, "box_caption": "0 0.001", "scores": {"class_score": 0.0010833740234375}, "domain": "pixel"}, {"position": {"minX": -22.40625, "minY": 179.875, "maxX": 118.875, "maxY": 300.25}, "class_id": 1, "box_caption": "panel 0.001", "scores": {"class_score": 0.0010833740234375}, "domain": "pixel"}, {"position": {"minX": 297.0, "minY": 52.28125, "maxX": 439.5, "maxY": 172.0}, "class_id": 1, "box_caption": "panel 0.001", "scores": {"class_score": 0.0010833740234375}, "domain": "pixel"}, {"position": {"minX": -56.4375, "minY": -11.65625, "maxX": 88.9375, "maxY": 107.625}, "class_id": 1, "box_caption": "panel 0.001", "scores": {"class_score": 0.0010824203491210938}, "domain": "pixel"}, {"position": {"minX": -56.1875, "minY": 212.0, "maxX": 88.5625, "maxY": 332.0}, "class_id": 1, "box_caption": "panel 0.001", "scores": {"class_score": 0.0010824203491210938}, "domain": "pixel"}, {"position": {"minX": -56.1875, "minY": 84.125, "maxX": 88.5625, "maxY": 203.875}, "class_id": 1, "box_caption": "panel 0.001", "scores": {"class_score": 0.0010824203491210938}, "domain": "pixel"}], "class_labels": {"0": "bus", "1": "panel", "2": "0", "3": "1", "4": "2", "5": "3", "6": "4", "7": "5", "8": "6", "9": "7", "10": "8", "11": "9", "12": "-"}}