{"box_data": [{"position": {"minX": 180.875, "minY": 27.6875, "maxX": 456.5, "maxY": 198.5}, "class_id": 0, "box_caption": "bus 0.157", "scores": {"class_score": 0.1573486328125}, "domain": "pixel"}, {"position": {"minX": 72.625, "minY": -7.125, "maxX": 410.0, "maxY": 231.5}, "class_id": 0, "box_caption": "bus 0.095", "scores": {"class_score": 0.0946044921875}, "domain": "pixel"}, {"position": {"minX": 154.125, "minY": 33.75, "maxX": 424.5, "maxY": 200.25}, "class_id": 1, "box_caption": "panel 0.070", "scores": {"class_score": 0.069580078125}, "domain": "pixel"}, {"position": {"minX": 117.875, "minY": 50.0, "maxX": 435.5, "maxY": 254.75}, "class_id": 0, "box_caption": "bus 0.046", "scores": {"class_score": 0.045745849609375}, "domain": "pixel"}, {"position": {"minX": 144.25, "minY": 78.0625, "maxX": 479.25, "maxY": 220.0}, "class_id": 0, "box_caption": "bus 0.045", "scores": {"class_score": 0.04486083984375}, "domain": "pixel"}, {"position": {"minX": 60.5, "minY": 29.375, "maxX": 375.0, "maxY": 189.75}, "class_id": 0, "box_caption": "bus 0.043", "scores": {"class_score": 0.043060302734375}, "domain": "pixel"}, {"position": {"minX": 201.0, "minY": -2.3125, "maxX": 407.0, "maxY": 164.5}, "class_id": 0, "box_caption": "bus 0.029", "scores": {"class_score": 0.0286102294921875}, "domain": "pixel"}, {"position": {"minX": 263.0, "minY": 45.6875, "maxX": 418.0, "maxY": 107.3125}, "class_id": 0, "box_caption": "bus 0.028", "scores": {"class_score": 0.02783203125}, "domain": "pixel"}, {"position": {"minX": 121.625, "minY": 178.5, "maxX": 129.75, "maxY": 202.5}, "class_id": 2, "box_caption": "0 0.025", "scores": {"class_score": 0.025146484375}, "domain": "pixel"}, {"position": {"minX": 108.75, "minY": 21.5, "maxX": 392.75, "maxY": 143.25}, "class_id": 0, "box_caption": "bus 0.024", "scores": {"class_score": 0.02398681640625}, "domain": "pixel"}, {"position": {"minX": 60.5, "minY": 29.375, "maxX": 375.0, "maxY": 189.75}, "class_id": 1, "box_caption": "panel 0.024", "scores": {"class_score": 0.0236358642578125}, "domain": "pixel"}, {"position": {"minX": 243.25, "minY": 70.1875, "maxX": 369.25, "maxY": 161.0}, "class_id": 1, "box_caption": "panel 0.023", "scores": {"class_score": 0.0225830078125}, "domain": "pixel"}, {"position": {"minX": 154.125, "minY": 33.75, "maxX": 424.5, "maxY": 200.25}, "class_id": 7, "box_caption": "5 0.022", "scores": {"class_score": 0.0217132568359375}, "domain": "pixel"}, {"position": {"minX": 112.5, "minY": 7.1875, "maxX": 415.0, "maxY": 203.75}, "class_id": 6, "box_caption": "4 0.021", "scores": {"class_score": 0.0207977294921875}, "domain": "pixel"}, {"position": {"minX": 247.75, "minY": 30.921875, "maxX": 431.25, "maxY": 82.0}, "class_id": 0, "box_caption": "bus 0.020", "scores": {"class_score": 0.019927978515625}, "domain": "pixel"}, {"position": {"minX": 103.375, "minY": -25.0, "maxX": 318.5, "maxY": 316.0}, "class_id": 0, "box_caption": "bus 0.020", "scores": {"class_score": 0.0196990966796875}, "domain": "pixel"}, {"position": {"minX": 112.5, "minY": 7.1875, "maxX": 415.0, "maxY": 203.75}, "class_id": 3, "box_caption": "1 0.020", "scores": {"class_score": 0.019500732421875}, "domain": "pixel"}, {"position": {"minX": 236.5, "minY": 36.875, "maxX": 456.5, "maxY": 181.25}, "class_id": 1, "box_caption": "panel 0.018", "scores": {"class_score": 0.0182647705078125}, "domain": "pixel"}, {"position": {"minX": 177.0, "minY": 4.1875, "maxX": 441.5, "maxY": 151.75}, "class_id": 1, "box_caption": "panel 0.018", "scores": {"class_score": 0.0179443359375}, "domain": "pixel"}, {"position": {"minX": 72.625, "minY": -7.125, "maxX": 410.0, "maxY": 231.5}, "class_id": 8, "box_caption": "6 0.018", "scores": {"class_score": 0.017578125}, "domain": "pixel"}, {"position": {"minX": 154.125, "minY": 33.75, "maxX": 424.5, "maxY": 200.25}, "class_id": 5, "box_caption": "3 0.017", "scores": {"class_score": 0.0174560546875}, "domain": "pixel"}, {"position": {"minX": 122.0625, "minY": 172.125, "maxX": 131.125, "maxY": 189.875}, "class_id": 2, "box_caption": "0 0.017", "scores": {"class_score": 0.017059326171875}, "domain": "pixel"}, {"position": {"minX": 108.75, "minY": 21.5, "maxX": 392.75, "maxY": 143.25}, "class_id": 1, "box_caption": "panel 0.017", "scores": {"class_score": 0.016754150390625}, "domain": "pixel"}, {"position": {"minX": 263.0, "minY": 45.6875, "maxX": 418.0, "maxY": 107.3125}, "class_id": 1, "box_caption": "panel 0.016", "scores": {"class_score": 0.0163421630859375}, "domain": "pixel"}, {"position": {"minX": 243.25, "minY": 70.1875, "maxX": 369.25, "maxY": 161.0}, "class_id": 3, "box_caption": "1 0.016", "scores": {"class_score": 0.016326904296875}, "domain": "pixel"}, {"position": {"minX": 252.75, "minY": 20.25, "maxX": 416.75, "maxY": 116.375}, "class_id": 0, "box_caption": "bus 0.016", "scores": {"class_score": 0.0162353515625}, "domain": "pixel"}, {"position": {"minX": 156.625, "minY": 24.1875, "maxX": 438.0, "maxY": 193.0}, "class_id": 8, "box_caption": "6 0.015", "scores": {"class_score": 0.01544189453125}, "domain": "pixel"}, {"position": {"minX": 297.25, "minY": 29.65625, "maxX": 442.75, "maxY": 129.625}, "class_id": 0, "box_caption": "bus 0.015", "scores": {"class_score": 0.0150909423828125}, "domain": "pixel"}, {"position": {"minX": 288.75, "minY": -18.5625, "maxX": 374.25, "maxY": 116.5625}, "class_id": 0, "box_caption": "bus 0.014", "scores": {"class_score": 0.01433563232421875}, "domain": "pixel"}, {"position": {"minX": 199.5, "minY": 140.5, "maxX": 234.0, "maxY": 165.5}, "class_id": 8, "box_caption": "6 0.014", "scores": {"class_score": 0.014129638671875}, "domain": "pixel"}, {"position": {"minX": 72.625, "minY": -7.125, "maxX": 410.0, "maxY": 231.5}, "class_id": 11, "box_caption": "9 0.014", "scores": {"class_score": 0.01396942138671875}, "domain": "pixel"}, {"position": {"minX": 72.625, "minY": -7.125, "maxX": 410.0, "maxY": 231.5}, "class_id": 1, "box_caption": "panel 0.014", "scores": {"class_score": 0.01375579833984375}, "domain": "pixel"}, {"position": {"minX": 156.625, "minY": 24.1875, "maxX": 438.0, "maxY": 193.0}, "class_id": 11, "box_caption": "9 0.014", "scores": {"class_score": 0.0136260986328125}, "domain": "pixel"}, {"position": {"minX": 108.75, "minY": 21.5, "maxX": 392.75, "maxY": 143.25}, "class_id": 7, "box_caption": "5 0.014", "scores": {"class_score": 0.01355743408203125}, "domain": "pixel"}, {"position": {"minX": 215.5, "minY": 119.875, "maxX": 412.5, "maxY": 225.125}, "class_id": 0, "box_caption": "bus 0.013", "scores": {"class_score": 0.01332855224609375}, "domain": "pixel"}, {"position": {"minX": 132.75, "minY": 173.75, "maxX": 134.5, "maxY": 194.25}, "class_id": 2, "box_caption": "0 0.013", "scores": {"class_score": 0.01305389404296875}, "domain": "pixel"}, {"position": {"minX": 72.625, "minY": -7.125, "maxX": 410.0, "maxY": 231.5}, "class_id": 2, "box_caption": "0 0.013", "scores": {"class_score": 0.012542724609375}, "domain": "pixel"}, {"position": {"minX": 243.25, "minY": 70.1875, "maxX": 369.25, "maxY": 161.0}, "class_id": 5, "box_caption": "3 0.012", "scores": {"class_score": 0.01214599609375}, "domain": "pixel"}, {"position": {"minX": 215.5, "minY": 119.875, "maxX": 412.5, "maxY": 225.125}, "class_id": 1, "box_caption": "panel 0.012", "scores": {"class_score": 0.01210784912109375}, "domain": "pixel"}, {"position": {"minX": 72.625, "minY": -7.125, "maxX": 410.0, "maxY": 231.5}, "class_id": 5, "box_caption": "3 0.012", "scores": {"class_score": 0.011962890625}, "domain": "pixel"}, {"position": {"minX": 72.625, "minY": -7.125, "maxX": 410.0, "maxY": 231.5}, "class_id": 9, "box_caption": "7 0.012", "scores": {"class_score": 0.01180267333984375}, "domain": "pixel"}, {"position": {"minX": 153.625, "minY": 31.75, "maxX": 424.0, "maxY": 251.0}, "class_id": 12, "box_caption": "- 0.011", "scores": {"class_score": 0.01143646240234375}, "domain": "pixel"}, {"position": {"minX": 224.375, "minY": 43.5, "maxX": 341.0, "maxY": 130.0}, "class_id": 1, "box_caption": "panel 0.011", "scores": {"class_score": 0.01117706298828125}, "domain": "pixel"}, {"position": {"minX": 186.875, "minY": 21.375, "maxX": 496.0, "maxY": 138.625}, "class_id": 0, "box_caption": "bus 0.011", "scores": {"class_score": 0.01102447509765625}, "domain": "pixel"}, {"position": {"minX": 243.25, "minY": 70.1875, "maxX": 369.25, "maxY": 161.0}, "class_id": 7, "box_caption": "5 0.011", "scores": {"class_score": 0.010894775390625}, "domain": "pixel"}, {"position": {"minX": 243.25, "minY": 70.1875, "maxX": 369.25, "maxY": 161.0}, "class_id": 8, "box_caption": "6 0.011", "scores": {"class_score": 0.0108642578125}, "domain": "pixel"}, {"position": {"minX": 199.5, "minY": 140.5, "maxX": 234.0, "maxY": 165.5}, "class_id": 2, "box_caption": "0 0.011", "scores": {"class_score": 0.0106964111328125}, "domain": "pixel"}, {"position": {"minX": 211.125, "minY": 139.0, "maxX": 243.375, "maxY": 169.25}, "class_id": 2, "box_caption": "0 0.011", "scores": {"class_score": 0.010650634765625}, "domain": "pixel"}, {"position": {"minX": 211.125, "minY": 139.0, "maxX": 243.375, "maxY": 169.25}, "class_id": 8, "box_caption": "6 0.010", "scores": {"class_score": 0.010467529296875}, "domain": "pixel"}, {"position": {"minX": 245.5, "minY": 42.6875, "maxX": 365.0, "maxY": 173.75}, "class_id": 12, "box_caption": "- 0.010", "scores": {"class_score": 0.0104217529296875}, "domain": "pixel"}, {"position": {"minX": 72.625, "minY": -7.125, "maxX": 410.0, "maxY": 231.5}, "class_id": 4, "box_caption": "2 0.010", "scores": {"class_score": 0.01038360595703125}, "domain": "pixel"}, {"position": {"minX": 214.5, "minY": 74.375, "maxX": 480.0, "maxY": 205.125}, "class_id": 1, "box_caption": "panel 0.010", "scores": {"class_score": 0.0102386474609375}, "domain": "pixel"}, {"position": {"minX": 302.75, "minY": 30.625, "maxX": 396.25, "maxY": 121.125}, "class_id": 0, "box_caption": "bus 0.010", "scores": {"class_score": 0.010162353515625}, "domain": "pixel"}, {"position": {"minX": 121.625, "minY": 178.5, "maxX": 129.75, "maxY": 202.5}, "class_id": 0, "box_caption": "bus 0.010", "scores": {"class_score": 0.0101165771484375}, "domain": "pixel"}, {"position": {"minX": 224.375, "minY": 43.5, "maxX": 341.0, "maxY": 130.0}, "class_id": 8, "box_caption": "6 0.010", "scores": {"class_score": 0.01007843017578125}, "domain": "pixel"}, {"position": {"minX": 247.75, "minY": 30.921875, "maxX": 431.25, "maxY": 82.0}, "class_id": 1, "box_caption": "panel 0.010", "scores": {"class_score": 0.0099639892578125}, "domain": "pixel"}, {"position": {"minX": 74.625, "minY": -36.75, "maxX": 348.0, "maxY": 262.5}, "class_id": 3, "box_caption": "1 0.010", "scores": {"class_score": 0.0098724365234375}, "domain": "pixel"}, {"position": {"minX": 177.0, "minY": 4.1875, "maxX": 441.5, "maxY": 151.75}, "class_id": 5, "box_caption": "3 0.010", "scores": {"class_score": 0.0095977783203125}, "domain": "pixel"}, {"position": {"minX": 72.625, "minY": -7.125, "maxX": 410.0, "maxY": 231.5}, "class_id": 10, "box_caption": "8 0.009", "scores": {"class_score": 0.00946807861328125}, "domain": "pixel"}, {"position": {"minX": 156.625, "minY": 24.1875, "maxX": 438.0, "maxY": 193.0}, "class_id": 2, "box_caption": "0 0.009", "scores": {"class_score": 0.00936126708984375}, "domain": "pixel"}, {"position": {"minX": 156.625, "minY": 24.1875, "maxX": 438.0, "maxY": 193.0}, "class_id": 9, "box_caption": "7 0.009", "scores": {"class_score": 0.009307861328125}, "domain": "pixel"}, {"position": {"minX": 60.5, "minY": 29.375, "maxX": 375.0, "maxY": 189.75}, "class_id": 7, "box_caption": "5 0.009", "scores": {"class_score": 0.00923919677734375}, "domain": "pixel"}, {"position": {"minX": 224.375, "minY": 43.5, "maxX": 341.0, "maxY": 130.0}, "class_id": 2, "box_caption": "0 0.009", "scores": {"class_score": 0.00917816162109375}, "domain": "pixel"}, {"position": {"minX": 171.0, "minY": 32.5625, "maxX": 463.0, "maxY": 251.25}, "class_id": 4, "box_caption": "2 0.009", "scores": {"class_score": 0.009033203125}, "domain": "pixel"}, {"position": {"minX": 156.625, "minY": 24.1875, "maxX": 438.0, "maxY": 193.0}, "class_id": 10, "box_caption": "8 0.009", "scores": {"class_score": 0.00891876220703125}, "domain": "pixel"}, {"position": {"minX": 245.5, "minY": 42.6875, "maxX": 365.0, "maxY": 173.75}, "class_id": 0, "box_caption": "bus 0.009", "scores": {"class_score": 0.0088958740234375}, "domain": "pixel"}, {"position": {"minX": 297.25, "minY": 29.65625, "maxX": 442.75, "maxY": 129.625}, "class_id": 1, "box_caption": "panel 0.009", "scores": {"class_score": 0.00875091552734375}, "domain": "pixel"}, {"position": {"minX": 121.625, "minY": 178.5, "maxX": 129.75, "maxY": 202.5}, "class_id": 3, "box_caption": "1 0.008", "scores": {"class_score": 0.00844573974609375}, "domain": "pixel"}, {"position": {"minX": 288.5, "minY": 4.625, "maxX": 407.0, "maxY": 207.125}, "class_id": 0, "box_caption": "bus 0.008", "scores": {"class_score": 0.00836944580078125}, "domain": "pixel"}, {"position": {"minX": 235.25, "minY": 141.125, "maxX": 265.5, "maxY": 171.375}, "class_id": 2, "box_caption": "0 0.008", "scores": {"class_score": 0.0082550048828125}, "domain": "pixel"}, {"position": {"minX": 122.0625, "minY": 172.125, "maxX": 131.125, "maxY": 189.875}, "class_id": 0, "box_caption": "bus 0.008", "scores": {"class_score": 0.00820159912109375}, "domain": "pixel"}, {"position": {"minX": 100.0, "minY": -6.875, "maxX": 382.5, "maxY": 284.0}, "class_id": 6, "box_caption": "4 0.008", "scores": {"class_score": 0.00806427001953125}, "domain": "pixel"}, {"position": {"minX": 177.0, "minY": 4.1875, "maxX": 441.5, "maxY": 151.75}, "class_id": 7, "box_caption": "5 0.008", "scores": {"class_score": 0.00794219970703125}, "domain": "pixel"}, {"position": {"minX": 220.875, "minY": 153.375, "maxX": 233.875, "maxY": 161.625}, "class_id": 2, "box_caption": "0 0.008", "scores": {"class_score": 0.00787353515625}, "domain": "pixel"}, {"position": {"minX": 108.75, "minY": 21.5, "maxX": 392.75, "maxY": 143.25}, "class_id": 5, "box_caption": "3 0.008", "scores": {"class_score": 0.00786590576171875}, "domain": "pixel"}, {"position": {"minX": 171.0, "minY": 32.5625, "maxX": 463.0, "maxY": 251.25}, "class_id": 3, "box_caption": "1 0.008", "scores": {"class_score": 0.0078277587890625}, "domain": "pixel"}, {"position": {"minX": 59.0625, "minY": 80.5, "maxX": 104.5625, "maxY": 138.875}, "class_id": 1, "box_caption": "panel 0.008", "scores": {"class_score": 0.007678985595703125}, "domain": "pixel"}, {"position": {"minX": 84.3125, "minY": 29.0, "maxX": 335.75, "maxY": 205.25}, "class_id": 4, "box_caption": "2 0.007", "scores": {"class_score": 0.0073699951171875}, "domain": "pixel"}, {"position": {"minX": 71.625, "minY": 86.125, "maxX": 123.625, "maxY": 131.625}, "class_id": 1, "box_caption": "panel 0.007", "scores": {"class_score": 0.0073089599609375}, "domain": "pixel"}, {"position": {"minX": 59.5, "minY": 82.375, "maxX": 571.5, "maxY": 276.0}, "class_id": 0, "box_caption": "bus 0.007", "scores": {"class_score": 0.007228851318359375}, "domain": "pixel"}, {"position": {"minX": 60.5, "minY": 29.375, "maxX": 375.0, "maxY": 189.75}, "class_id": 5, "box_caption": "3 0.007", "scores": {"class_score": 0.007175445556640625}, "domain": "pixel"}, {"position": {"minX": 224.375, "minY": 43.5, "maxX": 341.0, "maxY": 130.0}, "class_id": 3, "box_caption": "1 0.007", "scores": {"class_score": 0.00714874267578125}, "domain": "pixel"}, {"position": {"minX": 132.75, "minY": 173.75, "maxX": 134.5, "maxY": 194.25}, "class_id": 0, "box_caption": "bus 0.007", "scores": {"class_score": 0.007114410400390625}, "domain": "pixel"}, {"position": {"minX": 122.0625, "minY": 172.125, "maxX": 131.125, "maxY": 189.875}, "class_id": 7, "box_caption": "5 0.007", "scores": {"class_score": 0.0070648193359375}, "domain": "pixel"}, {"position": {"minX": 103.375, "minY": -25.0, "maxX": 318.5, "maxY": 316.0}, "class_id": 8, "box_caption": "6 0.007", "scores": {"class_score": 0.006999969482421875}, "domain": "pixel"}, {"position": {"minX": 119.5625, "minY": 164.625, "maxX": 149.75, "maxY": 184.125}, "class_id": 3, "box_caption": "1 0.007", "scores": {"class_score": 0.006961822509765625}, "domain": "pixel"}, {"position": {"minX": 121.625, "minY": 178.5, "maxX": 129.75, "maxY": 202.5}, "class_id": 1, "box_caption": "panel 0.007", "scores": {"class_score": 0.00681304931640625}, "domain": "pixel"}, {"position": {"minX": 204.25, "minY": 81.875, "maxX": 357.25, "maxY": 131.625}, "class_id": 2, "box_caption": "0 0.007", "scores": {"class_score": 0.00673675537109375}, "domain": "pixel"}, {"position": {"minX": 74.25, "minY": 183.375, "maxX": 121.25, "maxY": 220.625}, "class_id": 3, "box_caption": "1 0.007", "scores": {"class_score": 0.0067291259765625}, "domain": "pixel"}, {"position": {"minX": 243.25, "minY": 70.1875, "maxX": 369.25, "maxY": 161.0}, "class_id": 9, "box_caption": "7 0.007", "scores": {"class_score": 0.006572723388671875}, "domain": "pixel"}, {"position": {"minX": 11.125, "minY": 168.875, "maxX": 81.0625, "maxY": 227.625}, "class_id": 7, "box_caption": "5 0.006", "scores": {"class_score": 0.006412506103515625}, "domain": "pixel"}, {"position": {"minX": 236.875, "minY": 1.0, "maxX": 361.5, "maxY": 95.5}, "class_id": 0, "box_caption": "bus 0.006", "scores": {"class_score": 0.00640869140625}, "domain": "pixel"}, {"position": {"minX": 204.25, "minY": 81.875, "maxX": 357.25, "maxY": 131.625}, "class_id": 1, "box_caption": "panel 0.006", "scores": {"class_score": 0.0063934326171875}, "domain": "pixel"}, {"position": {"minX": 232.5, "minY": 120.8125, "maxX": 331.0, "maxY": 180.25}, "class_id": 5, "box_caption": "3 0.006", "scores": {"class_score": 0.006374359130859375}, "domain": "pixel"}, {"position": {"minX": 201.75, "minY": 4.875, "maxX": 414.75, "maxY": 162.25}, "class_id": 4, "box_caption": "2 0.006", "scores": {"class_score": 0.006328582763671875}, "domain": "pixel"}, {"position": {"minX": 279.0, "minY": 35.375, "maxX": 333.5, "maxY": 149.375}, "class_id": 12, "box_caption": "- 0.006", "scores": {"class_score": 0.006313323974609375}, "domain": "pixel"}, {"position": {"minX": 279.0, "minY": 35.375, "maxX": 333.5, "maxY": 149.375}, "class_id": 5, "box_caption": "3 0.006", "scores": {"class_score": 0.00629425048828125}, "domain": "pixel"}, {"position": {"minX": 209.875, "minY": 128.125, "maxX": 312.5, "maxY": 171.625}, "class_id": 1, "box_caption": "panel 0.006", "scores": {"class_score": 0.00629425048828125}, "domain": "pixel"}, {"position": {"minX": 224.375, "minY": 43.5, "maxX": 341.0, "maxY": 130.0}, "class_id": 5, "box_caption": "3 0.006", "scores": {"class_score": 0.00624847412109375}, "domain": "pixel"}, {"position": {"minX": 335.75, "minY": 186.0, "maxX": 371.25, "maxY": 211.5}, "class_id": 2, "box_caption": "0 0.006", "scores": {"class_score": 0.00621795654296875}, "domain": "pixel"}, {"position": {"minX": 119.5625, "minY": 164.625, "maxX": 149.75, "maxY": 184.125}, "class_id": 5, "box_caption": "3 0.006", "scores": {"class_score": 0.00618743896484375}, "domain": "pixel"}, {"position": {"minX": 121.625, "minY": 178.5, "maxX": 129.75, "maxY": 202.5}, "class_id": 7, "box_caption": "5 0.006", "scores": {"class_score": 0.006175994873046875}, "domain": "pixel"}, {"position": {"minX": 232.5, "minY": 120.8125, "maxX": 331.0, "maxY": 180.25}, "class_id": 2, "box_caption": "0 0.006", "scores": {"class_score": 0.00617218017578125}, "domain": "pixel"}, {"position": {"minX": 236.5, "minY": 36.875, "maxX": 456.5, "maxY": 181.25}, "class_id": 5, "box_caption": "3 0.006", "scores": {"class_score": 0.00617218017578125}, "domain": "pixel"}, {"position": {"minX": 316.0, "minY": 43.71875, "maxX": 443.5, "maxY": 166.5}, "class_id": 0, "box_caption": "bus 0.006", "scores": {"class_score": 0.0061492919921875}, "domain": "pixel"}, {"position": {"minX": 243.25, "minY": 70.1875, "maxX": 369.25, "maxY": 161.0}, "class_id": 2, "box_caption": "0 0.006", "scores": {"class_score": 0.006134033203125}, "domain": "pixel"}, {"position": {"minX": 122.0625, "minY": 172.125, "maxX": 131.125, "maxY": 189.875}, "class_id": 4, "box_caption": "2 0.006", "scores": {"class_score": 0.006114959716796875}, "domain": "pixel"}, {"position": {"minX": 74.25, "minY": 183.375, "maxX": 121.25, "maxY": 220.625}, "class_id": 6, "box_caption": "4 0.006", "scores": {"class_score": 0.006103515625}, "domain": "pixel"}, {"position": {"minX": 72.625, "minY": -7.125, "maxX": 410.0, "maxY": 231.5}, "class_id": 7, "box_caption": "5 0.006", "scores": {"class_score": 0.006084442138671875}, "domain": "pixel"}, {"position": {"minX": 122.0625, "minY": 172.125, "maxX": 131.125, "maxY": 189.875}, "class_id": 3, "box_caption": "1 0.006", "scores": {"class_score": 0.00605010986328125}, "domain": "pixel"}, {"position": {"minX": 84.3125, "minY": 29.0, "maxX": 335.75, "maxY": 205.25}, "class_id": 10, "box_caption": "8 0.006", "scores": {"class_score": 0.006015777587890625}, "domain": "pixel"}, {"position": {"minX": 236.875, "minY": 1.0, "maxX": 361.5, "maxY": 95.5}, "class_id": 1, "box_caption": "panel 0.006", "scores": {"class_score": 0.005924224853515625}, "domain": "pixel"}, {"position": {"minX": 279.0, "minY": 35.375, "maxX": 333.5, "maxY": 149.375}, "class_id": 0, "box_caption": "bus 0.006", "scores": {"class_score": 0.005870819091796875}, "domain": "pixel"}, {"position": {"minX": 121.625, "minY": 178.5, "maxX": 129.75, "maxY": 202.5}, "class_id": 6, "box_caption": "4 0.006", "scores": {"class_score": 0.005794525146484375}, "domain": "pixel"}, {"position": {"minX": 101.75, "minY": 12.3125, "maxX": 317.0, "maxY": 153.5}, "class_id": 4, "box_caption": "2 0.006", "scores": {"class_score": 0.005779266357421875}, "domain": "pixel"}, {"position": {"minX": 55.0, "minY": 54.65625, "maxX": 58.875, "maxY": 104.375}, "class_id": 1, "box_caption": "panel 0.006", "scores": {"class_score": 0.005771636962890625}, "domain": "pixel"}, {"position": {"minX": 311.5, "minY": -38.3125, "maxX": 409.0, "maxY": 140.75}, "class_id": 0, "box_caption": "bus 0.006", "scores": {"class_score": 0.00569915771484375}, "domain": "pixel"}, {"position": {"minX": 201.0, "minY": -2.3125, "maxX": 407.0, "maxY": 164.5}, "class_id": 8, "box_caption": "6 0.006", "scores": {"class_score": 0.005687713623046875}, "domain": "pixel"}, {"position": {"minX": 235.25, "minY": 141.125, "maxX": 265.5, "maxY": 171.375}, "class_id": 8, "box_caption": "6 0.006", "scores": {"class_score": 0.00567626953125}, "domain": "pixel"}, {"position": {"minX": 11.125, "minY": 168.875, "maxX": 81.0625, "maxY": 227.625}, "class_id": 4, "box_caption": "2 0.006", "scores": {"class_score": 0.00566864013671875}, "domain": "pixel"}, {"position": {"minX": 47.3125, "minY": 51.8125, "maxX": 178.25, "maxY": 241.25}, "class_id": 0, "box_caption": "bus 0.006", "scores": {"class_score": 0.0056610107421875}, "domain": "pixel"}, {"position": {"minX": 204.0, "minY": 146.875, "maxX": 263.0, "maxY": 157.375}, "class_id": 1, "box_caption": "panel 0.006", "scores": {"class_score": 0.005657196044921875}, "domain": "pixel"}, {"position": {"minX": 204.25, "minY": 81.875, "maxX": 357.25, "maxY": 131.625}, "class_id": 3, "box_caption": "1 0.006", "scores": {"class_score": 0.005611419677734375}, "domain": "pixel"}, {"position": {"minX": 121.625, "minY": 178.5, "maxX": 129.75, "maxY": 202.5}, "class_id": 8, "box_caption": "6 0.006", "scores": {"class_score": 0.0055694580078125}, "domain": "pixel"}, {"position": {"minX": 103.375, "minY": -25.0, "maxX": 318.5, "maxY": 316.0}, "class_id": 1, "box_caption": "panel 0.006", "scores": {"class_score": 0.0055389404296875}, "domain": "pixel"}, {"position": {"minX": 132.5, "minY": 181.375, "maxX": 133.75, "maxY": 207.125}, "class_id": 2, "box_caption": "0 0.006", "scores": {"class_score": 0.005535125732421875}, "domain": "pixel"}, {"position": {"minX": 201.0, "minY": -2.3125, "maxX": 407.0, "maxY": 164.5}, "class_id": 10, "box_caption": "8 0.006", "scores": {"class_score": 0.005527496337890625}, "domain": "pixel"}, {"position": {"minX": 103.375, "minY": -25.0, "maxX": 318.5, "maxY": 316.0}, "class_id": 9, "box_caption": "7 0.006", "scores": {"class_score": 0.005519866943359375}, "domain": "pixel"}, {"position": {"minX": 8.875, "minY": 172.25, "maxX": 61.875, "maxY": 228.0}, "class_id": 6, "box_caption": "4 0.005", "scores": {"class_score": 0.005443572998046875}, "domain": "pixel"}, {"position": {"minX": 236.5, "minY": 36.875, "maxX": 456.5, "maxY": 181.25}, "class_id": 7, "box_caption": "5 0.005", "scores": {"class_score": 0.0054168701171875}, "domain": "pixel"}, {"position": {"minX": 232.5, "minY": 120.8125, "maxX": 331.0, "maxY": 180.25}, "class_id": 1, "box_caption": "panel 0.005", "scores": {"class_score": 0.005367279052734375}, "domain": "pixel"}, {"position": {"minX": 271.75, "minY": -34.9375, "maxX": 342.75, "maxY": 131.5}, "class_id": 0, "box_caption": "bus 0.005", "scores": {"class_score": 0.005352020263671875}, "domain": "pixel"}, {"position": {"minX": 33.0, "minY": 38.1875, "maxX": 136.5, "maxY": 238.5}, "class_id": 11, "box_caption": "9 0.005", "scores": {"class_score": 0.00531005859375}, "domain": "pixel"}, {"position": {"minX": 245.0, "minY": 153.5, "maxX": 256.0, "maxY": 164.0}, "class_id": 2, "box_caption": "0 0.005", "scores": {"class_score": 0.00530242919921875}, "domain": "pixel"}, {"position": {"minX": 269.75, "minY": 30.8125, "maxX": 384.25, "maxY": 94.5625}, "class_id": 1, "box_caption": "panel 0.005", "scores": {"class_score": 0.005222320556640625}, "domain": "pixel"}, {"position": {"minX": 171.0, "minY": 32.5625, "maxX": 463.0, "maxY": 251.25}, "class_id": 6, "box_caption": "4 0.005", "scores": {"class_score": 0.005207061767578125}, "domain": "pixel"}, {"position": {"minX": 112.3125, "minY": 45.8125, "maxX": 114.8125, "maxY": 87.1875}, "class_id": 1, "box_caption": "panel 0.005", "scores": {"class_score": 0.0052032470703125}, "domain": "pixel"}, {"position": {"minX": 206.625, "minY": 142.625, "maxX": 260.0, "maxY": 154.875}, "class_id": 5, "box_caption": "3 0.005", "scores": {"class_score": 0.0052032470703125}, "domain": "pixel"}, {"position": {"minX": 263.0, "minY": 45.6875, "maxX": 418.0, "maxY": 107.3125}, "class_id": 5, "box_caption": "3 0.005", "scores": {"class_score": 0.00518035888671875}, "domain": "pixel"}, {"position": {"minX": 224.5, "minY": 98.0625, "maxX": 339.5, "maxY": 171.75}, "class_id": 5, "box_caption": "3 0.005", "scores": {"class_score": 0.005157470703125}, "domain": "pixel"}, {"position": {"minX": 83.25, "minY": 128.75, "maxX": 122.875, "maxY": 256.5}, "class_id": 4, "box_caption": "2 0.005", "scores": {"class_score": 0.005153656005859375}, "domain": "pixel"}, {"position": {"minX": 220.875, "minY": 153.375, "maxX": 233.875, "maxY": 161.625}, "class_id": 3, "box_caption": "1 0.005", "scores": {"class_score": 0.00513458251953125}, "domain": "pixel"}, {"position": {"minX": 201.0, "minY": -2.3125, "maxX": 407.0, "maxY": 164.5}, "class_id": 11, "box_caption": "9 0.005", "scores": {"class_score": 0.00510406494140625}, "domain": "pixel"}, {"position": {"minX": 103.375, "minY": -25.0, "maxX": 318.5, "maxY": 316.0}, "class_id": 11, "box_caption": "9 0.005", "scores": {"class_score": 0.005092620849609375}, "domain": "pixel"}, {"position": {"minX": 224.375, "minY": 43.5, "maxX": 341.0, "maxY": 130.0}, "class_id": 12, "box_caption": "- 0.005", "scores": {"class_score": 0.00507354736328125}, "domain": "pixel"}, {"position": {"minX": 119.6875, "minY": 123.625, "maxX": 311.75, "maxY": 215.875}, "class_id": 1, "box_caption": "panel 0.005", "scores": {"class_score": 0.0050506591796875}, "domain": "pixel"}, {"position": {"minX": 122.0625, "minY": 172.125, "maxX": 131.125, "maxY": 189.875}, "class_id": 8, "box_caption": "6 0.005", "scores": {"class_score": 0.005023956298828125}, "domain": "pixel"}, {"position": {"minX": 310.25, "minY": 113.75, "maxX": 370.75, "maxY": 146.75}, "class_id": 1, "box_caption": "panel 0.005", "scores": {"class_score": 0.005023956298828125}, "domain": "pixel"}, {"position": {"minX": -23.75, "minY": 46.1875, "maxX": 169.25, "maxY": 248.5}, "class_id": 0, "box_caption": "bus 0.005", "scores": {"class_score": 0.00499725341796875}, "domain": "pixel"}, {"position": {"minX": 37.65625, "minY": 100.3125, "maxX": 132.625, "maxY": 152.5}, "class_id": 1, "box_caption": "panel 0.005", "scores": {"class_score": 0.00498199462890625}, "domain": "pixel"}, {"position": {"minX": 212.0, "minY": 136.75, "maxX": 289.5, "maxY": 160.5}, "class_id": 1, "box_caption": "panel 0.005", "scores": {"class_score": 0.004940032958984375}, "domain": "pixel"}, {"position": {"minX": 328.0, "minY": 130.5, "maxX": 362.0, "maxY": 156.75}, "class_id": 1, "box_caption": "panel 0.005", "scores": {"class_score": 0.004932403564453125}, "domain": "pixel"}, {"position": {"minX": 99.875, "minY": 13.9375, "maxX": 381.0, "maxY": 170.5}, "class_id": 2, "box_caption": "0 0.005", "scores": {"class_score": 0.00492095947265625}, "domain": "pixel"}, {"position": {"minX": 279.0, "minY": 35.375, "maxX": 333.5, "maxY": 149.375}, "class_id": 1, "box_caption": "panel 0.005", "scores": {"class_score": 0.004901885986328125}, "domain": "pixel"}, {"position": {"minX": 204.25, "minY": 81.875, "maxX": 357.25, "maxY": 131.625}, "class_id": 5, "box_caption": "3 0.005", "scores": {"class_score": 0.00487518310546875}, "domain": "pixel"}, {"position": {"minX": 215.5, "minY": 119.875, "maxX": 412.5, "maxY": 225.125}, "class_id": 7, "box_caption": "5 0.005", "scores": {"class_score": 0.0048675537109375}, "domain": "pixel"}, {"position": {"minX": 108.75, "minY": 21.5, "maxX": 392.75, "maxY": 143.25}, "class_id": 3, "box_caption": "1 0.005", "scores": {"class_score": 0.004856109619140625}, "domain": "pixel"}, {"position": {"minX": 335.75, "minY": 186.0, "maxX": 371.25, "maxY": 211.5}, "class_id": 7, "box_caption": "5 0.005", "scores": {"class_score": 0.004772186279296875}, "domain": "pixel"}, {"position": {"minX": 204.25, "minY": 81.875, "maxX": 357.25, "maxY": 131.625}, "class_id": 9, "box_caption": "7 0.005", "scores": {"class_score": 0.0047607421875}, "domain": "pixel"}, {"position": {"minX": 33.0, "minY": 38.1875, "maxX": 136.5, "maxY": 238.5}, "class_id": 0, "box_caption": "bus 0.005", "scores": {"class_score": 0.0047454833984375}, "domain": "pixel"}, {"position": {"minX": 224.5, "minY": 98.0625, "maxX": 339.5, "maxY": 171.75}, "class_id": 1, "box_caption": "panel 0.005", "scores": {"class_score": 0.00472259521484375}, "domain": "pixel"}, {"position": {"minX": 302.75, "minY": 30.625, "maxX": 396.25, "maxY": 121.125}, "class_id": 6, "box_caption": "4 0.005", "scores": {"class_score": 0.00472259521484375}, "domain": "pixel"}, {"position": {"minX": 62.9375, "minY": -24.875, "maxX": 285.0, "maxY": 195.0}, "class_id": 0, "box_caption": "bus 0.005", "scores": {"class_score": 0.004718780517578125}, "domain": "pixel"}, {"position": {"minX": 132.75, "minY": 173.75, "maxX": 134.5, "maxY": 194.25}, "class_id": 3, "box_caption": "1 0.005", "scores": {"class_score": 0.0047149658203125}, "domain": "pixel"}, {"position": {"minX": 151.5, "minY": 127.125, "maxX": 346.75, "maxY": 221.625}, "class_id": 0, "box_caption": "bus 0.005", "scores": {"class_score": 0.00470733642578125}, "domain": "pixel"}, {"position": {"minX": 263.0, "minY": 45.6875, "maxX": 418.0, "maxY": 107.3125}, "class_id": 2, "box_caption": "0 0.005", "scores": {"class_score": 0.004695892333984375}, "domain": "pixel"}, {"position": {"minX": 232.5, "minY": 120.8125, "maxX": 331.0, "maxY": 180.25}, "class_id": 7, "box_caption": "5 0.005", "scores": {"class_score": 0.0046844482421875}, "domain": "pixel"}, {"position": {"minX": 204.25, "minY": 81.875, "maxX": 357.25, "maxY": 131.625}, "class_id": 12, "box_caption": "- 0.005", "scores": {"class_score": 0.004669189453125}, "domain": "pixel"}, {"position": {"minX": 182.75, "minY": 105.6875, "maxX": 374.25, "maxY": 134.375}, "class_id": 1, "box_caption": "panel 0.005", "scores": {"class_score": 0.0046539306640625}, "domain": "pixel"}, {"position": {"minX": 161.75, "minY": 19.6875, "maxX": 391.25, "maxY": 138.25}, "class_id": 2, "box_caption": "0 0.005", "scores": {"class_score": 0.004619598388671875}, "domain": "pixel"}, {"position": {"minX": 263.0, "minY": 45.6875, "maxX": 418.0, "maxY": 107.3125}, "class_id": 7, "box_caption": "5 0.005", "scores": {"class_score": 0.004619598388671875}, "domain": "pixel"}, {"position": {"minX": 73.125, "minY": 77.0625, "maxX": 117.375, "maxY": 108.3125}, "class_id": 1, "box_caption": "panel 0.005", "scores": {"class_score": 0.004608154296875}, "domain": "pixel"}, {"position": {"minX": 103.375, "minY": -25.0, "maxX": 318.5, "maxY": 316.0}, "class_id": 10, "box_caption": "8 0.005", "scores": {"class_score": 0.004543304443359375}, "domain": "pixel"}, {"position": {"minX": 288.75, "minY": -18.5625, "maxX": 374.25, "maxY": 116.5625}, "class_id": 10, "box_caption": "8 0.005", "scores": {"class_score": 0.004528045654296875}, "domain": "pixel"}, {"position": {"minX": 209.875, "minY": 128.125, "maxX": 312.5, "maxY": 171.625}, "class_id": 9, "box_caption": "7 0.005", "scores": {"class_score": 0.004505157470703125}, "domain": "pixel"}, {"position": {"minX": 204.25, "minY": 81.875, "maxX": 357.25, "maxY": 131.625}, "class_id": 7, "box_caption": "5 0.005", "scores": {"class_score": 0.0045013427734375}, "domain": "pixel"}, {"position": {"minX": 31.71875, "minY": 165.625, "maxX": 98.75, "maxY": 232.125}, "class_id": 3, "box_caption": "1 0.004", "scores": {"class_score": 0.004497528076171875}, "domain": "pixel"}, {"position": {"minX": 232.5, "minY": 120.8125, "maxX": 331.0, "maxY": 180.25}, "class_id": 9, "box_caption": "7 0.004", "scores": {"class_score": 0.004489898681640625}, "domain": "pixel"}, {"position": {"minX": 121.625, "minY": 178.5, "maxX": 129.75, "maxY": 202.5}, "class_id": 9, "box_caption": "7 0.004", "scores": {"class_score": 0.004486083984375}, "domain": "pixel"}, {"position": {"minX": 60.5, "minY": 29.375, "maxX": 375.0, "maxY": 189.75}, "class_id": 8, "box_caption": "6 0.004", "scores": {"class_score": 0.004486083984375}, "domain": "pixel"}, {"position": {"minX": 74.25, "minY": 183.375, "maxX": 121.25, "maxY": 220.625}, "class_id": 10, "box_caption": "8 0.004", "scores": {"class_score": 0.00446319580078125}, "domain": "pixel"}, {"position": {"minX": 15.453125, "minY": 86.3125, "maxX": 58.4375, "maxY": 124.6875}, "class_id": 6, "box_caption": "4 0.004", "scores": {"class_score": 0.004451751708984375}, "domain": "pixel"}, {"position": {"minX": 144.25, "minY": 78.0625, "maxX": 479.25, "maxY": 220.0}, "class_id": 9, "box_caption": "7 0.004", "scores": {"class_score": 0.004451751708984375}, "domain": "pixel"}, {"position": {"minX": 63.21875, "minY": 55.71875, "maxX": 65.5625, "maxY": 105.375}, "class_id": 1, "box_caption": "panel 0.004", "scores": {"class_score": 0.004436492919921875}, "domain": "pixel"}, {"position": {"minX": 144.25, "minY": 78.0625, "maxX": 479.25, "maxY": 220.0}, "class_id": 4, "box_caption": "2 0.004", "scores": {"class_score": 0.004436492919921875}, "domain": "pixel"}, {"position": {"minX": 279.0, "minY": 109.75, "maxX": 349.5, "maxY": 159.75}, "class_id": 1, "box_caption": "panel 0.004", "scores": {"class_score": 0.00439453125}, "domain": "pixel"}, {"position": {"minX": 110.3125, "minY": 50.1875, "maxX": 112.5625, "maxY": 93.9375}, "class_id": 3, "box_caption": "1 0.004", "scores": {"class_score": 0.004390716552734375}, "domain": "pixel"}, {"position": {"minX": 238.25, "minY": 135.25, "maxX": 274.25, "maxY": 207.25}, "class_id": 10, "box_caption": "8 0.004", "scores": {"class_score": 0.004390716552734375}, "domain": "pixel"}, {"position": {"minX": 132.75, "minY": 173.75, "maxX": 134.5, "maxY": 194.25}, "class_id": 6, "box_caption": "4 0.004", "scores": {"class_score": 0.004375457763671875}, "domain": "pixel"}, {"position": {"minX": 300.75, "minY": 13.84375, "maxX": 433.25, "maxY": 95.125}, "class_id": 0, "box_caption": "bus 0.004", "scores": {"class_score": 0.004367828369140625}, "domain": "pixel"}, {"position": {"minX": 33.0, "minY": 38.1875, "maxX": 136.5, "maxY": 238.5}, "class_id": 5, "box_caption": "3 0.004", "scores": {"class_score": 0.004364013671875}, "domain": "pixel"}, {"position": {"minX": 132.75, "minY": 173.75, "maxX": 134.5, "maxY": 194.25}, "class_id": 4, "box_caption": "2 0.004", "scores": {"class_score": 0.00434112548828125}, "domain": "pixel"}, {"position": {"minX": 252.75, "minY": 20.25, "maxX": 416.75, "maxY": 116.375}, "class_id": 11, "box_caption": "9 0.004", "scores": {"class_score": 0.00434112548828125}, "domain": "pixel"}, {"position": {"minX": 263.0, "minY": 45.6875, "maxX": 418.0, "maxY": 107.3125}, "class_id": 3, "box_caption": "1 0.004", "scores": {"class_score": 0.004329681396484375}, "domain": "pixel"}, {"position": {"minX": 75.875, "minY": 13.8125, "maxX": 288.0, "maxY": 133.75}, "class_id": 1, "box_caption": "panel 0.004", "scores": {"class_score": 0.0043182373046875}, "domain": "pixel"}, {"position": {"minX": 278.75, "minY": 37.90625, "maxX": 344.25, "maxY": 106.5}, "class_id": 0, "box_caption": "bus 0.004", "scores": {"class_score": 0.004314422607421875}, "domain": "pixel"}, {"position": {"minX": 112.3125, "minY": 45.8125, "maxX": 114.8125, "maxY": 87.1875}, "class_id": 3, "box_caption": "1 0.004", "scores": {"class_score": 0.004302978515625}, "domain": "pixel"}, {"position": {"minX": 263.0, "minY": 45.6875, "maxX": 418.0, "maxY": 107.3125}, "class_id": 11, "box_caption": "9 0.004", "scores": {"class_score": 0.0042877197265625}, "domain": "pixel"}, {"position": {"minX": 117.875, "minY": 50.0, "maxX": 435.5, "maxY": 254.75}, "class_id": 9, "box_caption": "7 0.004", "scores": {"class_score": 0.0042877197265625}, "domain": "pixel"}, {"position": {"minX": 263.0, "minY": 45.6875, "maxX": 418.0, "maxY": 107.3125}, "class_id": 4, "box_caption": "2 0.004", "scores": {"class_score": 0.00428009033203125}, "domain": "pixel"}, {"position": {"minX": 236.5, "minY": 36.875, "maxX": 456.5, "maxY": 181.25}, "class_id": 12, "box_caption": "- 0.004", "scores": {"class_score": 0.00428009033203125}, "domain": "pixel"}, {"position": {"minX": 245.0, "minY": 153.5, "maxX": 256.0, "maxY": 164.0}, "class_id": 3, "box_caption": "1 0.004", "scores": {"class_score": 0.004268646240234375}, "domain": "pixel"}, {"position": {"minX": 60.5, "minY": 29.375, "maxX": 375.0, "maxY": 189.75}, "class_id": 11, "box_caption": "9 0.004", "scores": {"class_score": 0.00426483154296875}, "domain": "pixel"}, {"position": {"minX": 212.75, "minY": 21.4375, "maxX": 452.75, "maxY": 196.5}, "class_id": 6, "box_caption": "4 0.004", "scores": {"class_score": 0.004241943359375}, "domain": "pixel"}, {"position": {"minX": 206.625, "minY": 142.625, "maxX": 260.0, "maxY": 154.875}, "class_id": 11, "box_caption": "9 0.004", "scores": {"class_score": 0.00423431396484375}, "domain": "pixel"}, {"position": {"minX": 31.71875, "minY": 165.625, "maxX": 98.75, "maxY": 232.125}, "class_id": 11, "box_caption": "9 0.004", "scores": {"class_score": 0.00423431396484375}, "domain": "pixel"}, {"position": {"minX": 75.875, "minY": 13.8125, "maxX": 288.0, "maxY": 133.75}, "class_id": 0, "box_caption": "bus 0.004", "scores": {"class_score": 0.004230499267578125}, "domain": "pixel"}, {"position": {"minX": 311.5, "minY": -38.3125, "maxX": 409.0, "maxY": 140.75}, "class_id": 10, "box_caption": "8 0.004", "scores": {"class_score": 0.004230499267578125}, "domain": "pixel"}, {"position": {"minX": 269.0, "minY": 17.375, "maxX": 480.0, "maxY": 141.0}, "class_id": 2, "box_caption": "0 0.004", "scores": {"class_score": 0.00421905517578125}, "domain": "pixel"}, {"position": {"minX": 201.75, "minY": 4.875, "maxX": 414.75, "maxY": 162.25}, "class_id": 2, "box_caption": "0 0.004", "scores": {"class_score": 0.0041961669921875}, "domain": "pixel"}, {"position": {"minX": 214.25, "minY": 104.6875, "maxX": 370.25, "maxY": 132.0}, "class_id": 3, "box_caption": "1 0.004", "scores": {"class_score": 0.004192352294921875}, "domain": "pixel"}, {"position": {"minX": 247.75, "minY": 30.921875, "maxX": 431.25, "maxY": 82.0}, "class_id": 2, "box_caption": "0 0.004", "scores": {"class_score": 0.00418853759765625}, "domain": "pixel"}, {"position": {"minX": 53.4375, "minY": 59.25, "maxX": 294.0, "maxY": 217.75}, "class_id": 1, "box_caption": "panel 0.004", "scores": {"class_score": 0.004184722900390625}, "domain": "pixel"}, {"position": {"minX": 312.75, "minY": 23.125, "maxX": 395.75, "maxY": 104.25}, "class_id": 3, "box_caption": "1 0.004", "scores": {"class_score": 0.004169464111328125}, "domain": "pixel"}, {"position": {"minX": 132.75, "minY": 173.75, "maxX": 134.5, "maxY": 194.25}, "class_id": 7, "box_caption": "5 0.004", "scores": {"class_score": 0.004154205322265625}, "domain": "pixel"}, {"position": {"minX": 224.375, "minY": 43.5, "maxX": 341.0, "maxY": 130.0}, "class_id": 6, "box_caption": "4 0.004", "scores": {"class_score": 0.004131317138671875}, "domain": "pixel"}, {"position": {"minX": 121.625, "minY": 178.5, "maxX": 129.75, "maxY": 202.5}, "class_id": 4, "box_caption": "2 0.004", "scores": {"class_score": 0.004123687744140625}, "domain": "pixel"}, {"position": {"minX": 177.0, "minY": 4.1875, "maxX": 441.5, "maxY": 151.75}, "class_id": 12, "box_caption": "- 0.004", "scores": {"class_score": 0.004123687744140625}, "domain": "pixel"}, {"position": {"minX": 279.0, "minY": 109.75, "maxX": 349.5, "maxY": 159.75}, "class_id": 5, "box_caption": "3 0.004", "scores": {"class_score": 0.004119873046875}, "domain": "pixel"}, {"position": {"minX": 297.25, "minY": 29.65625, "maxX": 442.75, "maxY": 129.625}, "class_id": 5, "box_caption": "3 0.004", "scores": {"class_score": 0.004119873046875}, "domain": "pixel"}, {"position": {"minX": 60.5, "minY": 29.375, "maxX": 375.0, "maxY": 189.75}, "class_id": 12, "box_caption": "- 0.004", "scores": {"class_score": 0.00411224365234375}, "domain": "pixel"}, {"position": {"minX": 112.3125, "minY": 45.8125, "maxX": 114.8125, "maxY": 87.1875}, "class_id": 2, "box_caption": "0 0.004", "scores": {"class_score": 0.004108428955078125}, "domain": "pixel"}, {"position": {"minX": 212.75, "minY": 21.4375, "maxX": 452.75, "maxY": 196.5}, "class_id": 3, "box_caption": "1 0.004", "scores": {"class_score": 0.00406646728515625}, "domain": "pixel"}, {"position": {"minX": 211.125, "minY": 139.0, "maxX": 243.375, "maxY": 169.25}, "class_id": 3, "box_caption": "1 0.004", "scores": {"class_score": 0.003997802734375}, "domain": "pixel"}, {"position": {"minX": 232.5, "minY": 120.8125, "maxX": 331.0, "maxY": 180.25}, "class_id": 8, "box_caption": "6 0.004", "scores": {"class_score": 0.003993988037109375}, "domain": "pixel"}, {"position": {"minX": 67.375, "minY": 62.375, "maxX": 370.5, "maxY": 240.875}, "class_id": 4, "box_caption": "2 0.004", "scores": {"class_score": 0.003986358642578125}, "domain": "pixel"}, {"position": {"minX": 229.125, "minY": 138.5, "maxX": 256.75, "maxY": 172.75}, "class_id": 8, "box_caption": "6 0.004", "scores": {"class_score": 0.003978729248046875}, "domain": "pixel"}, {"position": {"minX": 120.125, "minY": 159.75, "maxX": 165.875, "maxY": 190.0}, "class_id": 3, "box_caption": "1 0.004", "scores": {"class_score": 0.003978729248046875}, "domain": "pixel"}, {"position": {"minX": 214.5, "minY": 74.375, "maxX": 480.0, "maxY": 205.125}, "class_id": 5, "box_caption": "3 0.004", "scores": {"class_score": 0.003971099853515625}, "domain": "pixel"}, {"position": {"minX": 119.5625, "minY": 164.625, "maxX": 149.75, "maxY": 184.125}, "class_id": 2, "box_caption": "0 0.004", "scores": {"class_score": 0.00396728515625}, "domain": "pixel"}, {"position": {"minX": 182.125, "minY": 40.9375, "maxX": 197.125, "maxY": 97.6875}, "class_id": 1, "box_caption": "panel 0.004", "scores": {"class_score": 0.00395965576171875}, "domain": "pixel"}, {"position": {"minX": 209.875, "minY": 128.125, "maxX": 312.5, "maxY": 171.625}, "class_id": 5, "box_caption": "3 0.004", "scores": {"class_score": 0.00395965576171875}, "domain": "pixel"}, {"position": {"minX": 74.25, "minY": 183.375, "maxX": 121.25, "maxY": 220.625}, "class_id": 11, "box_caption": "9 0.004", "scores": {"class_score": 0.0039520263671875}, "domain": "pixel"}, {"position": {"minX": 214.5, "minY": 74.375, "maxX": 480.0, "maxY": 205.125}, "class_id": 7, "box_caption": "5 0.004", "scores": {"class_score": 0.003948211669921875}, "domain": "pixel"}, {"position": {"minX": 256.5, "minY": 138.125, "maxX": 287.5, "maxY": 203.625}, "class_id": 10, "box_caption": "8 0.004", "scores": {"class_score": 0.003925323486328125}, "domain": "pixel"}, {"position": {"minX": 74.25, "minY": 183.375, "maxX": 121.25, "maxY": 220.625}, "class_id": 9, "box_caption": "7 0.004", "scores": {"class_score": 0.003925323486328125}, "domain": "pixel"}, {"position": {"minX": 256.5, "minY": 138.125, "maxX": 287.5, "maxY": 203.625}, "class_id": 1, "box_caption": "panel 0.004", "scores": {"class_score": 0.00391387939453125}, "domain": "pixel"}, {"position": {"minX": 137.875, "minY": 58.8125, "maxX": 229.625, "maxY": 145.75}, "class_id": 5, "box_caption": "3 0.004", "scores": {"class_score": 0.003910064697265625}, "domain": "pixel"}, {"position": {"minX": 247.75, "minY": 30.921875, "maxX": 431.25, "maxY": 82.0}, "class_id": 5, "box_caption": "3 0.004", "scores": {"class_score": 0.00390625}, "domain": "pixel"}, {"position": {"minX": 195.375, "minY": 135.5, "maxX": 247.875, "maxY": 158.0}, "class_id": 2, "box_caption": "0 0.004", "scores": {"class_score": 0.00389862060546875}, "domain": "pixel"}, {"position": {"minX": 1.4375, "minY": 40.75, "maxX": 163.75, "maxY": 179.375}, "class_id": 5, "box_caption": "3 0.004", "scores": {"class_score": 0.0038967132568359375}, "domain": "pixel"}, {"position": {"minX": 103.375, "minY": -25.0, "maxX": 318.5, "maxY": 316.0}, "class_id": 5, "box_caption": "3 0.004", "scores": {"class_score": 0.003894805908203125}, "domain": "pixel"}, {"position": {"minX": 268.5, "minY": 4.0625, "maxX": 400.5, "maxY": 150.75}, "class_id": 6, "box_caption": "4 0.004", "scores": {"class_score": 0.003879547119140625}, "domain": "pixel"}, {"position": {"minX": 228.75, "minY": 143.375, "maxX": 236.0, "maxY": 170.625}, "class_id": 2, "box_caption": "0 0.004", "scores": {"class_score": 0.0038776397705078125}, "domain": "pixel"}, {"position": {"minX": 46.03125, "minY": 165.0, "maxX": 47.96875, "maxY": 187.5}, "class_id": 3, "box_caption": "1 0.004", "scores": {"class_score": 0.0038661956787109375}, "domain": "pixel"}, {"position": {"minX": 55.15625, "minY": 179.875, "maxX": 115.125, "maxY": 242.375}, "class_id": 7, "box_caption": "5 0.004", "scores": {"class_score": 0.0038509368896484375}, "domain": "pixel"}, {"position": {"minX": 204.25, "minY": 81.875, "maxX": 357.25, "maxY": 131.625}, "class_id": 0, "box_caption": "bus 0.004", "scores": {"class_score": 0.0038509368896484375}, "domain": "pixel"}, {"position": {"minX": 242.25, "minY": 126.9375, "maxX": 290.25, "maxY": 190.875}, "class_id": 1, "box_caption": "panel 0.004", "scores": {"class_score": 0.0038509368896484375}, "domain": "pixel"}, {"position": {"minX": 12.5, "minY": 94.0, "maxX": 146.0, "maxY": 255.5}, "class_id": 11, "box_caption": "9 0.004", "scores": {"class_score": 0.00384521484375}, "domain": "pixel"}, {"position": {"minX": 144.25, "minY": 78.0625, "maxX": 479.25, "maxY": 220.0}, "class_id": 10, "box_caption": "8 0.004", "scores": {"class_score": 0.003818511962890625}, "domain": "pixel"}, {"position": {"minX": 20.875, "minY": 83.25, "maxX": 74.25, "maxY": 96.625}, "class_id": 1, "box_caption": "panel 0.004", "scores": {"class_score": 0.0038166046142578125}, "domain": "pixel"}, {"position": {"minX": -3.0625, "minY": 143.0, "maxX": 114.625, "maxY": 202.0}, "class_id": 11, "box_caption": "9 0.004", "scores": {"class_score": 0.0038166046142578125}, "domain": "pixel"}, {"position": {"minX": 327.75, "minY": 188.375, "maxX": 365.25, "maxY": 207.625}, "class_id": 1, "box_caption": "panel 0.004", "scores": {"class_score": 0.0038127899169921875}, "domain": "pixel"}, {"position": {"minX": 224.5, "minY": 98.0625, "maxX": 339.5, "maxY": 171.75}, "class_id": 12, "box_caption": "- 0.004", "scores": {"class_score": 0.003810882568359375}, "domain": "pixel"}, {"position": {"minX": 236.875, "minY": 1.0, "maxX": 361.5, "maxY": 95.5}, "class_id": 2, "box_caption": "0 0.004", "scores": {"class_score": 0.0038013458251953125}, "domain": "pixel"}, {"position": {"minX": 224.375, "minY": 43.5, "maxX": 341.0, "maxY": 130.0}, "class_id": 10, "box_caption": "8 0.004", "scores": {"class_score": 0.0037841796875}, "domain": "pixel"}, {"position": {"minX": 11.125, "minY": 168.875, "maxX": 81.0625, "maxY": 227.625}, "class_id": 2, "box_caption": "0 0.004", "scores": {"class_score": 0.003757476806640625}, "domain": "pixel"}, {"position": {"minX": 8.875, "minY": 172.25, "maxX": 61.875, "maxY": 228.0}, "class_id": 3, "box_caption": "1 0.004", "scores": {"class_score": 0.0037555694580078125}, "domain": "pixel"}, {"position": {"minX": 103.375, "minY": -25.0, "maxX": 318.5, "maxY": 316.0}, "class_id": 4, "box_caption": "2 0.004", "scores": {"class_score": 0.003753662109375}, "domain": "pixel"}, {"position": {"minX": 1.125, "minY": 88.5, "maxX": 89.25, "maxY": 159.0}, "class_id": 1, "box_caption": "panel 0.004", "scores": {"class_score": 0.0037441253662109375}, "domain": "pixel"}, {"position": {"minX": 122.0625, "minY": 172.125, "maxX": 131.125, "maxY": 189.875}, "class_id": 6, "box_caption": "4 0.004", "scores": {"class_score": 0.0037364959716796875}, "domain": "pixel"}, {"position": {"minX": 211.125, "minY": 158.375, "maxX": 250.125, "maxY": 174.125}, "class_id": 1, "box_caption": "panel 0.004", "scores": {"class_score": 0.0037364959716796875}, "domain": "pixel"}, {"position": {"minX": 8.875, "minY": 172.25, "maxX": 61.875, "maxY": 228.0}, "class_id": 11, "box_caption": "9 0.004", "scores": {"class_score": 0.00373077392578125}, "domain": "pixel"}, {"position": {"minX": 31.71875, "minY": 165.625, "maxX": 98.75, "maxY": 232.125}, "class_id": 6, "box_caption": "4 0.004", "scores": {"class_score": 0.0037174224853515625}, "domain": "pixel"}, {"position": {"minX": 269.75, "minY": 30.8125, "maxX": 384.25, "maxY": 94.5625}, "class_id": 12, "box_caption": "- 0.004", "scores": {"class_score": 0.0037097930908203125}, "domain": "pixel"}, {"position": {"minX": 84.3125, "minY": 29.0, "maxX": 335.75, "maxY": 205.25}, "class_id": 9, "box_caption": "7 0.004", "scores": {"class_score": 0.0037078857421875}, "domain": "pixel"}, {"position": {"minX": 47.3125, "minY": 51.8125, "maxX": 178.25, "maxY": 241.25}, "class_id": 11, "box_caption": "9 0.004", "scores": {"class_score": 0.0037021636962890625}, "domain": "pixel"}, {"position": {"minX": 67.375, "minY": 62.375, "maxX": 370.5, "maxY": 240.875}, "class_id": 10, "box_caption": "8 0.004", "scores": {"class_score": 0.0036907196044921875}, "domain": "pixel"}, {"position": {"minX": 108.75, "minY": 21.5, "maxX": 392.75, "maxY": 143.25}, "class_id": 11, "box_caption": "9 0.004", "scores": {"class_score": 0.003688812255859375}, "domain": "pixel"}, {"position": {"minX": 15.125, "minY": 81.8125, "maxX": 58.4375, "maxY": 110.8125}, "class_id": 6, "box_caption": "4 0.004", "scores": {"class_score": 0.0036869049072265625}, "domain": "pixel"}, {"position": {"minX": 122.0625, "minY": 172.125, "maxX": 131.125, "maxY": 189.875}, "class_id": 5, "box_caption": "3 0.004", "scores": {"class_score": 0.00368499755859375}, "domain": "pixel"}, {"position": {"minX": 335.75, "minY": 186.0, "maxX": 371.25, "maxY": 211.5}, "class_id": 1, "box_caption": "panel 0.004", "scores": {"class_score": 0.003681182861328125}, "domain": "pixel"}, {"position": {"minX": 204.0, "minY": 146.875, "maxX": 263.0, "maxY": 157.375}, "class_id": 9, "box_caption": "7 0.004", "scores": {"class_score": 0.0036792755126953125}, "domain": "pixel"}, {"position": {"minX": 236.5, "minY": 36.875, "maxX": 456.5, "maxY": 181.25}, "class_id": 11, "box_caption": "9 0.004", "scores": {"class_score": 0.0036792755126953125}, "domain": "pixel"}, {"position": {"minX": 177.0, "minY": 4.1875, "maxX": 441.5, "maxY": 151.75}, "class_id": 3, "box_caption": "1 0.004", "scores": {"class_score": 0.0036773681640625}, "domain": "pixel"}, {"position": {"minX": 263.0, "minY": 45.6875, "maxX": 418.0, "maxY": 107.3125}, "class_id": 12, "box_caption": "- 0.004", "scores": {"class_score": 0.0036773681640625}, "domain": "pixel"}, {"position": {"minX": 28.5, "minY": 69.4375, "maxX": 68.625, "maxY": 81.6875}, "class_id": 10, "box_caption": "8 0.004", "scores": {"class_score": 0.003673553466796875}, "domain": "pixel"}, {"position": {"minX": 243.25, "minY": 70.1875, "maxX": 369.25, "maxY": 161.0}, "class_id": 6, "box_caption": "4 0.004", "scores": {"class_score": 0.0036640167236328125}, "domain": "pixel"}, {"position": {"minX": 224.375, "minY": 43.5, "maxX": 341.0, "maxY": 130.0}, "class_id": 11, "box_caption": "9 0.004", "scores": {"class_score": 0.0036449432373046875}, "domain": "pixel"}, {"position": {"minX": 108.75, "minY": 21.5, "maxX": 392.75, "maxY": 143.25}, "class_id": 8, "box_caption": "6 0.004", "scores": {"class_score": 0.0036411285400390625}, "domain": "pixel"}, {"position": {"minX": 18.3125, "minY": 173.25, "maxX": 93.25, "maxY": 246.0}, "class_id": 7, "box_caption": "5 0.004", "scores": {"class_score": 0.00363922119140625}, "domain": "pixel"}, {"position": {"minX": 236.5, "minY": 36.875, "maxX": 456.5, "maxY": 181.25}, "class_id": 4, "box_caption": "2 0.004", "scores": {"class_score": 0.00363922119140625}, "domain": "pixel"}, {"position": {"minX": 297.25, "minY": 29.65625, "maxX": 442.75, "maxY": 129.625}, "class_id": 11, "box_caption": "9 0.004", "scores": {"class_score": 0.003631591796875}, "domain": "pixel"}, {"position": {"minX": -3.0625, "minY": 143.0, "maxX": 114.625, "maxY": 202.0}, "class_id": 3, "box_caption": "1 0.004", "scores": {"class_score": 0.003631591796875}, "domain": "pixel"}, {"position": {"minX": 191.25, "minY": -29.28125, "maxX": 494.75, "maxY": 126.375}, "class_id": 10, "box_caption": "8 0.004", "scores": {"class_score": 0.0036258697509765625}, "domain": "pixel"}, {"position": {"minX": 92.875, "minY": 167.625, "maxX": 114.375, "maxY": 221.625}, "class_id": 4, "box_caption": "2 0.004", "scores": {"class_score": 0.0036220550537109375}, "domain": "pixel"}, {"position": {"minX": 211.125, "minY": 139.0, "maxX": 243.375, "maxY": 169.25}, "class_id": 7, "box_caption": "5 0.004", "scores": {"class_score": 0.0036163330078125}, "domain": "pixel"}, {"position": {"minX": 101.75, "minY": 12.3125, "maxX": 317.0, "maxY": 153.5}, "class_id": 10, "box_caption": "8 0.004", "scores": {"class_score": 0.0036163330078125}, "domain": "pixel"}, {"position": {"minX": 242.25, "minY": 126.9375, "maxX": 290.25, "maxY": 190.875}, "class_id": 5, "box_caption": "3 0.004", "scores": {"class_score": 0.0036106109619140625}, "domain": "pixel"}, {"position": {"minX": 199.5, "minY": 140.5, "maxX": 234.0, "maxY": 165.5}, "class_id": 4, "box_caption": "2 0.004", "scores": {"class_score": 0.0035953521728515625}, "domain": "pixel"}, {"position": {"minX": 215.5, "minY": 119.875, "maxX": 412.5, "maxY": 225.125}, "class_id": 4, "box_caption": "2 0.004", "scores": {"class_score": 0.003589630126953125}, "domain": "pixel"}, {"position": {"minX": 11.6875, "minY": 164.5, "maxX": 124.9375, "maxY": 247.75}, "class_id": 11, "box_caption": "9 0.004", "scores": {"class_score": 0.0035858154296875}, "domain": "pixel"}, {"position": {"minX": 212.0, "minY": 136.75, "maxX": 289.5, "maxY": 160.5}, "class_id": 5, "box_caption": "3 0.004", "scores": {"class_score": 0.0035800933837890625}, "domain": "pixel"}, {"position": {"minX": 119.5625, "minY": 164.625, "maxX": 149.75, "maxY": 184.125}, "class_id": 11, "box_caption": "9 0.004", "scores": {"class_score": 0.003574371337890625}, "domain": "pixel"}, {"position": {"minX": 20.875, "minY": 83.25, "maxX": 74.25, "maxY": 96.625}, "class_id": 6, "box_caption": "4 0.004", "scores": {"class_score": 0.003574371337890625}, "domain": "pixel"}, {"position": {"minX": 316.0, "minY": 43.71875, "maxX": 443.5, "maxY": 166.5}, "class_id": 1, "box_caption": "panel 0.004", "scores": {"class_score": 0.003566741943359375}, "domain": "pixel"}, {"position": {"minX": -4.4375, "minY": -63.375, "maxX": 164.5, "maxY": 320.5}, "class_id": 6, "box_caption": "4 0.004", "scores": {"class_score": 0.0035610198974609375}, "domain": "pixel"}, {"position": {"minX": 221.0, "minY": 146.625, "maxX": 277.5, "maxY": 180.875}, "class_id": 1, "box_caption": "panel 0.004", "scores": {"class_score": 0.0035533905029296875}, "domain": "pixel"}, {"position": {"minX": 215.5, "minY": 119.875, "maxX": 412.5, "maxY": 225.125}, "class_id": 5, "box_caption": "3 0.004", "scores": {"class_score": 0.003543853759765625}, "domain": "pixel"}, {"position": {"minX": 215.5, "minY": 119.875, "maxX": 412.5, "maxY": 225.125}, "class_id": 11, "box_caption": "9 0.004", "scores": {"class_score": 0.003543853759765625}, "domain": "pixel"}], "class_labels": {"0": "bus", "1": "panel", "2": "0", "3": "1", "4": "2", "5": "3", "6": "4", "7": "5", "8": "6", "9": "7", "10": "8", "11": "9", "12": "-"}}